Register-File/Register-File.v
module registerFile (
    input rst, clk, writeEnable,
    input [31 : 0] dataWrite, addressWrite, addressA, addressB,
    output reg [31 : 0] dataA, dataB
);
    integer  i;
    reg [31 : 0] registerFileData [31 : 0];

    always @(posedge clk, posedge rst) begin
        if(rst)
            for(i = 0; i < 32; i++)
                registerFileData[i] <= 0;
        else if(writeEnable)
            registerFileData[addressWrite] = dataWrite;
    end

    always@(*)begin
        dataA = registerFileData[addressA];
        dataB = registerFileData[addressB];
    end

endmodule

Register-File/testbench.v
`include "Register-File.v"

module tb;

    reg  [31 : 0] addressA, addressB,addressWrite, dataWrite;
    reg writeEnable, clk, rst;         
    wire [31 : 0] dataA, dataB;


    registerFile dut(.addressA(addressA), .addressB(addressB), .addressWrite(addressWrite), .writeEnable(writeEnable), .dataWrite(dataWrite), .dataA(dataA), .dataB(dataB), .rst(rst), .clk(clk));

    always #10 clk ^= 1;

    initial begin
        clk = 0; // init clk
        $dumpfile("testbench.vcd");
        $dumpvars(0, tb);

        // resetting

        rst = 1;
        #10
        rst = 0;

        addressA = 10;
        addressB = 11;

        // writing

        @(negedge clk);
        dataWrite = 8'h55;
        addressWrite = 9;
        writeEnable = 1;
        
        @(negedge clk);
        dataWrite = 4'b1111;
        addressWrite = 10;
        
        @(negedge clk);
        dataWrite = 4'b1100;
        addressWrite = 11;

        writeEnable = 0;

        //reading
        @(negedge clk);
        addressA = 9;
        addressB = 10;
        
        @(negedge clk);
        addressA = 10;
        addressB = 9;
        
        @(negedge clk);
        addressA = 10;
        addressB = 11;

        #50


        $finish;

    end

endmodule

Register-File/testbench.vcd
$date
	Wed Jun 26 23:43:21 2024
$end
$version
	Icarus Verilog
$end
$timescale
	1s
$end
$scope module tb $end
$var wire 32 ! dataB [31:0] $end
$var wire 32 " dataA [31:0] $end
$var reg 32 # addressA [31:0] $end
$var reg 32 $ addressB [31:0] $end
$var reg 32 % addressWrite [31:0] $end
$var reg 1 & clk $end
$var reg 32 ' dataWrite [31:0] $end
$var reg 1 ( rst $end
$var reg 1 ) writeEnable $end
$scope module dut $end
$var wire 32 * addressA [31:0] $end
$var wire 32 + addressB [31:0] $end
$var wire 32 , addressWrite [31:0] $end
$var wire 1 & clk $end
$var wire 32 - dataWrite [31:0] $end
$var wire 1 ( rst $end
$var wire 1 ) writeEnable $end
$var reg 32 . dataA [31:0] $end
$var reg 32 / dataB [31:0] $end
$var integer 32 0 i [31:0] $end
$upscope $end
$upscope $end
$enddefinitions $end
$comment Show the parameter values. $end
$dumpall
$end
#0
$dumpvars
b100000 0
bx /
bx .
bx -
bx ,
bx +
bx *
x)
1(
bx '
0&
bx %
bx $
bx #
bx "
bx !
$end
#10
b0 !
b0 /
b0 "
b0 .
b1011 $
b1011 +
b1010 #
b1010 *
0(
1&
#20
1)
b1001 %
b1001 ,
b1010101 '
b1010101 -
0&
#30
1&
#40
b1010 %
b1010 ,
b1111 '
b1111 -
0&
#50
b1111 "
b1111 .
1&
#60
0)
b1011 %
b1011 ,
b1100 '
b1100 -
0&
#70
1&
#80
b1111 !
b1111 /
b1010101 "
b1010101 .
b1010 $
b1010 +
b1001 #
b1001 *
0&
#90
1&
#100
b1010101 !
b1010101 /
b1111 "
b1111 .
b1001 $
b1001 +
b1010 #
b1010 *
0&
#110
1&
#120
b0 !
b0 /
b1011 $
b1011 +
0&
