Register-File/Register-File.v
module registerFile (
    input rst, clk, writeEnable,
    input [31 : 0] dataWrite, 
    input [4 : 0] addressWrite, addressA, addressB,
    output reg [31 : 0] dataA, dataB,

    // for testing

    input [4 : 0]addressTest, 
    output reg [31 : 0] outputTest
);
    integer  i;
    reg [31 : 0] registerFileData [31 : 0];

    always @(posedge clk, posedge rst) begin
        if(rst)
            for(i = 0; i < 32; i++)
                registerFileData[i] <= 0;
        else if(writeEnable)
            registerFileData[addressWrite] = dataWrite;
    end



    always@(*)begin
        outputTest = registerFileData[addressTest];
        dataA = registerFileData[addressA];
        dataB = registerFileData[addressB];
    end

endmodule

Program-Counter/Program_Counter.v
module programCounter (
    input clk, rst, en,
    input [31 : 0] dataInput,
    output reg [31 : 0] dataOutput
);
    always @(posedge clk, posedge rst) begin
        if(rst)
            dataOutput <= 0;
        else if(en)
            dataOutput <=  dataInput;
    end
endmodule

ALU/alu.v

module ALU(
    input      [31 : 0] SrcA, SrcB,
    input      [2 : 0] ALUControl,
    output reg [31 : 0]ALUResult);

localparam 
add = 3'b010,
sub = 3'b110,
andd= 3'b000,
orr = 3'b001, // ignore for now
slt = 3'b111; // ignore for now

always @(*) begin
    case (ALUControl)
        add :  ALUResult = SrcA + SrcB;
        sub :  ALUResult = SrcA - SrcB;
        andd:  ALUResult = SrcA & SrcB;
        default: ALUResult = 0;
    endcase
end


endmodule

Data-Memory/Data_Memory.v
// 1kb data memory for MIPS microarch

module dataMemory (
    input               clk, rst, writeEnable,
    input      [31 : 0] address, dataWrite,
    output [31 : 0] dataOutput
);
    
    reg [31 : 0] data [1023 : 0];
    integer  i;
    always @(posedge clk, posedge rst) begin
        if(rst)begin
            for(i = 1;i < 1024;i++)
                data[i] <= 0;
            data[0] <= 32'h8C0A0020;                              // lw $t1, 32($0)
            data[1] <= 32'b000000_10100_01010_01010_00000_100010; // add $t1, $t1, $some other register
            data[32]<= 32'h00000005;                              // $t1 = 0x05;
        end
        else if(writeEnable)   
                data[address] <= dataWrite;
    end

    assign dataOutput = data[address];
endmodule

data_path.v
`include "Data-Memory/Data_Memory.v"
`include "ALU/alu.v"
`include "Register-File/Register-File.v"
`include "Program-Counter/Program_Counter.v"

module dataPath(
    input         rst, clk,
    // controls from l to r
    input         PCEn, IorD, Memwrite, IRWrite, 
                  RegDst, MemtoReg, RegWrite, ALUsrcA,
    input [1 : 0] ALUsrcB, 
    input [2 : 0] ALUControl,
    input PCsrc,
    // for testing register file
    input [4 : 0] addressTest,
    output [31 : 0] outputTest,
    // for controller
    output [5 : 0] opcode, funct
    );

    //controller out
    assign opcode = Instr[31 : 26];
    assign funct  = Instr[5 : 0];

    // SignImm
    wire [31 : 0] SignImm;
    assign SignImm = {Instr[15]?16'hffff : 16'h0000 , Instr[15 : 0]};

    // data/instruction memory ins and outs
    wire [31 : 0] Adr, dataOutput;
    reg [31 : 0] Instr, Data;
    always @(posedge clk)
        if(IRWrite)
            Instr <= dataOutput;
    always @(posedge clk)
        Data  <= dataOutput;
    assign Adr = IorD?ALUOut:PC;
    dataMemory m(.clk(clk), .rst(rst), .writeEnable(Memwrite), .address(Adr), .dataWrite(B), .dataOutput(dataOutput));

    
    // ALU ins and outs
    wire[31 : 0] ALUResult;
    reg [31 : 0] SrcA, SrcB, ALUOut;
    always @(posedge clk)ALUOut <= ALUResult;
    ALU a(.SrcA(SrcA), .SrcB(SrcB), .ALUControl(ALUControl), .ALUResult(ALUResult));
    always @(*) begin
        case (ALUsrcA)
            0:SrcA = PC;
            1:SrcA = A;
            default: SrcA = 0;
        endcase
        case (ALUsrcB)
            0:SrcB = B;
            1:SrcB = 1; // for simplicty it's word addressable
            2:SrcB = SignImm;
            3:SrcB = SignImm << 2;
            default: SrcB = 0;
        endcase
    end
    
    // PC ins and outs
    wire [31 : 0] PCPrime, PC;
    assign PCPrime = PCsrc ? ALUOut : ALUResult;
    programCounter p(.en(PCEn), .rst(rst), .dataInput(PCPrime), .clk(clk), .dataOutput(PC));

    // RF ins and outs
    wire [31 : 0]RwriteData;
    wire [4 : 0] Radr;
    assign Radr = RegDst?Instr[15 : 11] : Instr[20 : 16];
    assign RwriteData = MemtoReg?Data : ALUOut;
    wire [31 : 0] atmp, btmp;
    reg [31 : 0] A, B;
    always @(posedge clk)begin
        A<=atmp;
        B<=btmp;
    end
    registerFile r(.clk(clk), .rst(rst), .writeEnable(RegWrite), .dataWrite(RwriteData),
                   .addressWrite(Radr), .addressA(Instr[25 : 21]), .addressB(Instr[20 : 16]),
                   .dataA(atmp), .dataB(btmp), .addressTest(addressTest),
                    .outputTest(outputTest));
endmodule



/** TODO : maybe unify MemtoReg and RegDst as one line
 ** Maybe add rst to the non-architectural registers, although it's unnecessary. 
 ** the only register that needs rst is PC. 
 ** Change the data/instruction memory to byte addressable and concatenate the bytes.
**/

control_unit.v
module controller (
    input [5 : 0] opcode, funct,
    input         rst, clk,

    // controls from l to r
    output reg    PCEn, IorD, Memwrite, IRWrite, 
                  RegDst, MemtoReg, RegWrite, ALUsrcA,
    output reg [1 : 0] ALUsrcB, 
    output reg [2 : 0] ALUControl,
    output reg PCsrc
);
    // opcodes
    localparam rType = 6'b000000,
               lw    = 6'b100011,
               sw    = 6'b101011,
               beq   = 6'b000100;

    // funct fields
    localparam add = 6'b100000,
               sub = 6'b100010;

    // states
    localparam fetch     = 0,
               decode    = 1,
               execute1  = 2,
               execute2  = 3,
               execute3  = 4, // at most 3 cycles
               writeBack = 5;
    

    reg [2 : 0] currState, nextState;
    always @(negedge clk, posedge rst)begin
        if(rst)currState <= 0;
        else currState <= nextState;
    end

    always @(*) begin
        // next state compute, edit for all instructions
        case (currState)
            fetch : nextState <= decode;
            decode : nextState <= execute1;
            execute1 : nextState <= execute2;
            execute2 : begin
                case (opcode)
                    lw : nextState <= execute3; 
                    rType : nextState <= fetch;
                    default: nextState <= fetch;
                endcase
            end 
            execute3:nextState <= fetch;
            default: nextState <= fetch;
        endcase

        // output compute
        casez (currState)
            fetch : begin
                // writes
                Memwrite  = 0;
                RegWrite  = 0;
                IRWrite   = 1;
                PCEn      = 1;
                // muxes
                IorD      = 0;
                RegDst    = 0;
                MemtoReg  = 0;
                ALUsrcA   = 0;
                ALUsrcB   = 1;
                ALUControl= 2;
                PCsrc     = 0;
            end 

            decode : begin
                // writes
                Memwrite  = 0;
                RegWrite  = 0;
                IRWrite   = 0;
                PCEn      = 0;
            end

            execute1: begin
                case (opcode)
                    lw : begin
                        // writes
                        Memwrite  = 0;
                        RegWrite  = 0;
                        IRWrite   = 0;
                        PCEn      = 0;
                        // muxes
                        IorD      = 0;
                        RegDst    = 0;
                        MemtoReg  = 0;
                        ALUsrcA   = 1;
                        ALUsrcB   = 2;
                        ALUControl= 2;
                        PCsrc     = 0;
                    end 
                    rType: begin
                        // writes
                        Memwrite  = 0;
                        RegWrite  = 0;
                        IRWrite   = 0;
                        PCEn      = 0;
                        // muxes
                        IorD      = 0;
                        RegDst    = 0;
                        MemtoReg  = 0;
                        ALUsrcA   = 1;
                        ALUsrcB   = 0;
                        PCsrc     = 0;
                        case (funct)
                            add : ALUControl = 2;
                            sub : ALUControl = 6;
                            default: ALUControl = 2;
                        endcase
                    end
                    default: PCsrc = 0; // invalid instruction
                endcase
            end

            execute2: begin
                case (opcode)
                        lw: begin
                            // writes
                            Memwrite  = 0;
                            RegWrite  = 0;
                            IRWrite   = 0;
                            PCEn      = 0;
                            // muxes
                            IorD      = 1;
                            RegDst    = 0;
                            MemtoReg  = 0;
                            ALUsrcA   = 0;
                            ALUsrcB   = 0;
                            ALUControl= 0;
                            PCsrc     = 0;
                        end
                        rType: begin
                            // writes
                            Memwrite  = 0;
                            RegWrite  = 1;
                            IRWrite   = 0;
                            PCEn      = 0;
                            // muxes
                            IorD      = 0;
                            RegDst    = 1;
                            MemtoReg  = 0;
                            ALUsrcA   = 0;
                            ALUsrcB   = 0;
                            ALUControl= 0;
                            PCsrc     = 0;
                        end
                    default: PCsrc = 0;
                endcase
            end

            execute3: begin
                case (opcode)
                    lw:begin
                        // writes
                        Memwrite  = 0;
                        RegWrite  = 1;
                        IRWrite   = 0;
                        PCEn      = 0;
                        // muxes
                        IorD      = 0;
                        RegDst    = 0;
                        MemtoReg  = 1;
                        ALUsrcA   = 0;
                        ALUsrcB   = 0;
                        ALUControl= 0;
                        PCsrc     = 0;
                    end
                    default: PCsrc = 0;
                endcase
            end            
            default: PCsrc = 0;
        endcase        
    end

endmodule


// TODO insert the don't cares instead of the dumb shit you did.

/*
    // writes
    Memwrite  = 0;
    RegWrite  = 0;
    IRWrite   = 1;
    PCEn      = 1;
    // muxes
    IorD      = 0;
    RegDst    = 0;
    MemtoReg  = 0;
    ALUsrcA   = 0;
    ALUsrcB   = 1;
    ALUControl= 2;
    PCsrc     = 0;
*/

mips.v
`include "control_unit.v"
`include "data_path.v"

module MIPS(input clk, rst,
            input [4 : 0] addressTest);

    wire [5 : 0] opcode, funct;
    wire         PCEn, IorD, Memwrite, IRWrite, RegDst, MemtoReg, RegWrite, ALUsrcA,PCsrc;
    wire [1 : 0] ALUsrcB;
    wire [2 : 0] ALUControl;

    controller cu(.clk(clk), .rst(rst), .opcode(opcode), .funct(funct), .PCEn(PCEn), .IorD(IorD), 
                .Memwrite(Memwrite), .IRWrite(IRWrite), .RegDst(RegDst), .MemtoReg(MemtoReg), .RegWrite(RegWrite),
                .ALUsrcA(ALUsrcA),.PCsrc(PCsrc), .ALUsrcB(ALUsrcB), .ALUControl(ALUControl));

    dataPath   dp(.rst(rst), .clk(clk), .PCEn(PCEn), .IorD(IorD), .Memwrite(Memwrite),
                  .IRWrite(IRWrite), . RegDst( RegDst), .MemtoReg(MemtoReg), .RegWrite(RegWrite),
                  .ALUsrcA(ALUsrcA), .ALUsrcB(ALUsrcB), . ALUControl( ALUControl), .PCsrc(PCsrc), 
                  .addressTest(addressTest), .opcode(opcode), .funct(funct)); 
endmodule

mips_testbench.v
`include "mips.v"
`timescale 1ns/1ps
module tb;

    reg clk, rst;
    reg [4 : 0] addressTest;

    MIPS d(clk, rst, addressTest);

    always #10 clk ^= 1;

    initial begin
        $dumpfile("mips_testbench.vcd");
        $dumpvars(0, tb);
        clk = 0;

        rst = 1;
        #5;
        rst = 0;

        addressTest = 10;
        #200;
        $finish;
    end

endmodule

mips_testbench.vcd
$date
	Fri Jul  5 17:12:16 2024
$end
$version
	Icarus Verilog
$end
$timescale
	1ps
$end
$scope module tb $end
$var reg 5 ! addressTest [4:0] $end
$var reg 1 " clk $end
$var reg 1 # rst $end
$scope module d $end
$var wire 5 $ addressTest [4:0] $end
$var wire 1 " clk $end
$var wire 1 # rst $end
$var wire 6 % opcode [5:0] $end
$var wire 6 & funct [5:0] $end
$var wire 1 ' RegWrite $end
$var wire 1 ( RegDst $end
$var wire 1 ) PCsrc $end
$var wire 1 * PCEn $end
$var wire 1 + Memwrite $end
$var wire 1 , MemtoReg $end
$var wire 1 - IorD $end
$var wire 1 . IRWrite $end
$var wire 2 / ALUsrcB [1:0] $end
$var wire 1 0 ALUsrcA $end
$var wire 3 1 ALUControl [2:0] $end
$scope module cu $end
$var wire 1 " clk $end
$var wire 1 # rst $end
$var wire 6 2 opcode [5:0] $end
$var wire 6 3 funct [5:0] $end
$var parameter 6 4 add $end
$var parameter 6 5 beq $end
$var parameter 32 6 decode $end
$var parameter 32 7 execute1 $end
$var parameter 32 8 execute2 $end
$var parameter 32 9 execute3 $end
$var parameter 32 : fetch $end
$var parameter 6 ; lw $end
$var parameter 6 < rType $end
$var parameter 6 = sub $end
$var parameter 6 > sw $end
$var parameter 32 ? writeBack $end
$var reg 3 @ ALUControl [2:0] $end
$var reg 1 0 ALUsrcA $end
$var reg 2 A ALUsrcB [1:0] $end
$var reg 1 . IRWrite $end
$var reg 1 - IorD $end
$var reg 1 , MemtoReg $end
$var reg 1 + Memwrite $end
$var reg 1 * PCEn $end
$var reg 1 ) PCsrc $end
$var reg 1 ( RegDst $end
$var reg 1 ' RegWrite $end
$var reg 3 B currState [2:0] $end
$var reg 3 C nextState [2:0] $end
$upscope $end
$scope module dp $end
$var wire 3 D ALUControl [2:0] $end
$var wire 1 0 ALUsrcA $end
$var wire 2 E ALUsrcB [1:0] $end
$var wire 1 . IRWrite $end
$var wire 1 - IorD $end
$var wire 1 , MemtoReg $end
$var wire 1 + Memwrite $end
$var wire 1 * PCEn $end
$var wire 1 ) PCsrc $end
$var wire 1 ( RegDst $end
$var wire 1 ' RegWrite $end
$var wire 5 F addressTest [4:0] $end
$var wire 1 " clk $end
$var wire 1 # rst $end
$var wire 32 G outputTest [31:0] $end
$var wire 6 H opcode [5:0] $end
$var wire 6 I funct [5:0] $end
$var wire 32 J dataOutput [31:0] $end
$var wire 32 K btmp [31:0] $end
$var wire 32 L atmp [31:0] $end
$var wire 32 M SignImm [31:0] $end
$var wire 32 N RwriteData [31:0] $end
$var wire 5 O Radr [4:0] $end
$var wire 32 P PCPrime [31:0] $end
$var wire 32 Q PC [31:0] $end
$var wire 32 R Adr [31:0] $end
$var wire 32 S ALUResult [31:0] $end
$var reg 32 T A [31:0] $end
$var reg 32 U ALUOut [31:0] $end
$var reg 32 V B [31:0] $end
$var reg 32 W Data [31:0] $end
$var reg 32 X Instr [31:0] $end
$var reg 32 Y SrcA [31:0] $end
$var reg 32 Z SrcB [31:0] $end
$scope module a $end
$var wire 3 [ ALUControl [2:0] $end
$var wire 32 \ SrcA [31:0] $end
$var wire 32 ] SrcB [31:0] $end
$var parameter 3 ^ add $end
$var parameter 3 _ andd $end
$var parameter 3 ` orr $end
$var parameter 3 a slt $end
$var parameter 3 b sub $end
$var reg 32 c ALUResult [31:0] $end
$upscope $end
$scope module m $end
$var wire 32 d address [31:0] $end
$var wire 1 " clk $end
$var wire 32 e dataOutput [31:0] $end
$var wire 32 f dataWrite [31:0] $end
$var wire 1 # rst $end
$var wire 1 + writeEnable $end
$var integer 32 g i [31:0] $end
$upscope $end
$scope module p $end
$var wire 1 " clk $end
$var wire 32 h dataInput [31:0] $end
$var wire 1 * en $end
$var wire 1 # rst $end
$var reg 32 i dataOutput [31:0] $end
$upscope $end
$scope module r $end
$var wire 5 j addressA [4:0] $end
$var wire 5 k addressB [4:0] $end
$var wire 5 l addressTest [4:0] $end
$var wire 5 m addressWrite [4:0] $end
$var wire 1 " clk $end
$var wire 32 n dataWrite [31:0] $end
$var wire 1 # rst $end
$var wire 1 ' writeEnable $end
$var reg 32 o dataA [31:0] $end
$var reg 32 p dataB [31:0] $end
$var reg 32 q outputTest [31:0] $end
$var integer 32 r i [31:0] $end
$upscope $end
$upscope $end
$upscope $end
$upscope $end
$enddefinitions $end
$comment Show the parameter values. $end
$dumpall
b110 b
b111 a
b1 `
b0 _
b10 ^
b101 ?
b101011 >
b100010 =
b0 <
b100011 ;
b0 :
b100 9
b11 8
b10 7
b1 6
b100 5
b100000 4
$end
#0
$dumpvars
b10100 r
bx q
bx p
bx o
bx n
bx m
bx l
bx k
bx j
b0 i
b1 h
b10000000000 g
bx f
b10001100000010100000000000100000 e
b0 d
b1 c
b1 ]
b0 \
b10 [
b1 Z
b0 Y
bx X
bx W
bx V
bx U
bx T
b1 S
b0 R
b0 Q
b1 P
bx O
bx N
bx M
bx L
bx K
b10001100000010100000000000100000 J
bx I
bx H
bx G
bx F
b1 E
b10 D
b1 C
b0 B
b1 A
b10 @
bx 3
bx 2
b10 1
00
b1 /
1.
0-
0,
0+
1*
0)
0(
0'
bx &
bx %
bx $
1#
0"
bx !
$end
#5000
b0 G
b0 q
b1010 !
b1010 $
b1010 F
b1010 l
0#
#10000
b10 P
b10 h
b1010 O
b1010 m
b0 K
b0 p
b0 L
b0 o
b10 S
b10 c
b100011 %
b100011 2
b100011 H
b100000 &
b100000 3
b100000 I
b100000 M
b0 j
b1010 k
b1 N
b1 n
b10100010100101000000100010 J
b10100010100101000000100010 e
b1 R
b1 d
b1 Y
b1 \
b10001100000010100000000000100000 X
b10001100000010100000000000100000 W
b1 U
b1 Q
b1 i
1"
#20000
b10 C
0*
0.
b1 B
0"
#30000
b10 N
b10 n
b0 V
b0 f
b0 T
b10 U
b10100010100101000000100010 W
1"
#40000
b11 C
b100000 P
b100000 h
b100000 S
b100000 c
b100000 Z
b100000 ]
b0 Y
b0 \
b10 /
b10 A
b10 E
10
b10 B
0"
#50000
b100000 N
b100000 n
b100000 U
1"
#60000
b100 C
b0 P
b0 h
b0 S
b0 c
b0 Z
b0 ]
b1 Y
b1 \
b101 J
b101 e
b100000 R
b100000 d
b0 1
b0 @
b0 D
b0 [
b0 /
b0 A
b0 E
00
1-
b11 B
0"
#70000
b10001100000010100000000000100000 J
b10001100000010100000000000100000 e
b0 R
b0 d
b0 N
b0 n
b0 U
b101 W
1"
#80000
b0 C
b101 N
b101 n
b10100010100101000000100010 J
b10100010100101000000100010 e
b1 R
b1 d
1,
0-
1'
b100 B
0"
#90000
b10100010100101000000100010 N
b10100010100101000000100010 n
b10100010100101000000100010 W
b101 K
b101 p
b101 G
b101 q
1"
#100000
b1 C
b10 P
b10 h
b10 S
b10 c
b1 Z
b1 ]
b0 N
b0 n
b10 1
b10 @
b10 D
b10 [
b1 /
b1 A
b1 E
0,
1*
1.
0'
b0 B
0"
#110000
b11 P
b11 h
b1010 L
b1010 o
b11 S
b11 c
b10 N
b10 n
b0 %
b0 2
b0 H
b100010 &
b100010 3
b100010 I
b101000000100010 M
b10100 j
b0 J
b0 e
b10 R
b10 d
b10 Y
b10 \
b101 V
b101 f
b10 U
b10100010100101000000100010 X
b10 Q
b10 i
1"
#120000
b10 C
0*
0.
b1 B
0"
#130000
b11 N
b11 n
b0 W
b11 U
b1010 T
1"
#140000
b11 C
b101 P
b101 h
b101 S
b101 c
b101 Z
b101 ]
b1010 Y
b1010 \
b110 1
b110 @
b110 D
b110 [
b0 /
b0 A
b0 E
10
b10 B
0"
#150000
b101 N
b101 n
b101 U
1"
#160000
b0 C
b0 P
b0 h
b0 S
b0 c
b10 Y
b10 \
b0 1
b0 @
b0 D
b0 [
00
1(
1'
b11 B
0"
#170000
b0 N
b0 n
b0 U
1"
#180000
b1 C
b11 P
b11 h
b11 S
b11 c
b1 Z
b1 ]
b10 1
b10 @
b10 D
b10 [
b1 /
b1 A
b1 E
0(
1*
1.
0'
b0 B
0"
#190000
b100 P
b100 h
b0 O
b0 m
b0 K
b0 p
b0 L
b0 o
b100 S
b100 c
b11 N
b11 n
b0 &
b0 3
b0 I
b0 M
b0 j
b0 k
b11 R
b11 d
b11 Y
b11 \
b11 U
b0 X
b11 Q
b11 i
1"
#200000
b10 C
0*
0.
b1 B
0"
