Register-File/Register-File.v
module registerFile (
    input rst, clk, writeEnable,
    input [31 : 0] dataWrite, 
    input [4 : 0] addressWrite, addressA, addressB,
    output reg [31 : 0] dataA, dataB,

    // for testing

    input [4 : 0]addressTest, 
    output reg [31 : 0] outputTest
);
    integer  i;
    reg [31 : 0] registerFileData [31 : 0];

    always @(posedge clk, posedge rst) begin
        if(rst)
            for(i = 0; i < 32; i++)
                registerFileData[i] <= 0;
        else if(writeEnable)
            registerFileData[addressWrite] = dataWrite;
    end



    always@(*)begin
        outputTest = registerFileData[addressTest];
        dataA = registerFileData[addressA];
        dataB = registerFileData[addressB];
    end

endmodule

Program-Counter/Program_Counter.v
module programCounter (
    input clk, rst, en,
    input [31 : 0] dataInput,
    output reg [31 : 0] dataOutput
);
    always @(posedge clk, posedge rst) begin
        if(rst)
            dataOutput <= 0;
        else if(en)
            dataOutput <=  dataInput;
    end
endmodule

ALU/alu.v

module ALU(
    input      [31 : 0] SrcA, SrcB,
    input      [2 : 0] ALUControl,
    output reg [31 : 0]ALUResult);

localparam 
add = 3'b010,
sub = 3'b110,
andd= 3'b000,
orr = 3'b001, // ignore for now
slt = 3'b111; // ignore for now

always @(*) begin
    case (ALUControl)
        add :  ALUResult = SrcA + SrcB;
        sub :  ALUResult = SrcA - SrcB;
        andd:  ALUResult = SrcA & SrcB;
        default: ALUResult = 0;
    endcase
end


endmodule

Data-Memory/Data_Memory.v
// 1kb data memory for MIPS microarch

module dataMemory (
    input               clk, rst, writeEnable,
    input      [31 : 0] address, dataWrite,
    output [31 : 0] dataOutput
);
    
    reg [31 : 0] data [1023 : 0];
    integer  i;
    always @(posedge clk, posedge rst) begin
        if(rst)begin
            for(i = 1;i < 1024;i++)
                data[i] <= 0;
            
            // test
            // data[32]<= 32'h00000005;                              // $t1 = 0x05;

            // data[0] <= 32'h8C0A0020;                              // lw $t1, 32($0), t1 = 5
            // data[1] <= 32'b000100_01010_01010_0000000000000011;   // beq $t1, $t1, add(5)
            // data[5] <= 32'b000000_10100_01010_01010_00000_100000; // add $t1, $t1, $some other register
            
        end
        else if(writeEnable)   
                data[address] <= dataWrite;
    end

    assign dataOutput = data[address];
endmodule

data_path.v
`include "Data-Memory/Data_Memory.v"
`include "ALU/alu.v"
`include "Register-File/Register-File.v"
`include "Program-Counter/Program_Counter.v"

module dataPath(
    input         rst, clk,
    // controls from l to r
    input         PCEn, IorD, Memwrite, IRWrite, 
                  RegDst, MemtoReg, RegWrite, ALUsrcA,
    input [1 : 0] ALUsrcB, 
    input [2 : 0] ALUControl,
    input PCsrc,
    // for testing register file
    input [4 : 0] addressTest,
    output [31 : 0] outputTest,
    // for controller
    output [5 : 0] opcode, funct,
    output zero
    );

    //controller out
    assign opcode = Instr[31 : 26];
    assign funct  = Instr[5 : 0];

    // SignImm
    wire [31 : 0] SignImm;
    assign SignImm = {Instr[15]?16'hffff : 16'h0000 , Instr[15 : 0]};

    // data/instruction memory ins and outs
    wire [31 : 0] Adr, dataOutput;
    reg [31 : 0] Instr, Data;
    always @(posedge clk)
        if(IRWrite)
            Instr <= dataOutput;
    always @(posedge clk)
        Data  <= dataOutput;
    assign Adr = IorD?ALUOut:PC;
    dataMemory m(.clk(clk), .rst(rst), .writeEnable(Memwrite), .address(Adr), .dataWrite(B), .dataOutput(dataOutput));

    
    // ALU ins and outs
    assign zero = (ALUResult == 0);
    wire[31 : 0] ALUResult;
    reg [31 : 0] SrcA, SrcB, ALUOut;
    always @(posedge clk)ALUOut <= ALUResult;
    ALU a(.SrcA(SrcA), .SrcB(SrcB), .ALUControl(ALUControl), .ALUResult(ALUResult));
    always @(*) begin
        case (ALUsrcA)
            0:SrcA = PC;
            1:SrcA = A;
            default: SrcA = 0;
        endcase
        case (ALUsrcB)
            0:SrcB = B;
            1:SrcB = 1; // for simplicty it's word addressable
            2:SrcB = SignImm;
            3:SrcB = SignImm;
            default: SrcB = 0;
        endcase
    end
    
    // PC ins and outs
    wire [31 : 0] PCPrime, PC;
    assign PCPrime = PCsrc ? ALUOut : ALUResult;
    programCounter p(.en(PCEn), .rst(rst), .dataInput(PCPrime), .clk(clk), .dataOutput(PC));

    // RF ins and outs
    wire [31 : 0]RwriteData;
    wire [4 : 0] Radr;
    assign Radr = RegDst?Instr[15 : 11] : Instr[20 : 16];
    assign RwriteData = MemtoReg?Data : ALUOut;
    wire [31 : 0] atmp, btmp;
    reg [31 : 0] A, B;
    always @(posedge clk)begin
        A<=atmp;
        B<=btmp;
    end
    registerFile r(.clk(clk), .rst(rst), .writeEnable(RegWrite), .dataWrite(RwriteData),
                   .addressWrite(Radr), .addressA(Instr[25 : 21]), .addressB(Instr[20 : 16]),
                   .dataA(atmp), .dataB(btmp), .addressTest(addressTest),
                    .outputTest(outputTest));
endmodule



/** TODO : maybe unify MemtoReg and RegDst as one line
 ** Maybe add rst to the non-architectural registers, although it's unnecessary. 
 ** the only register that needs rst is PC. 
 ** Change the data/instruction memory to byte addressable and concatenate the bytes.
**/

control_unit.v
module controller (
    input [5 : 0] opcode, funct,
    input         rst, clk,
    input         zero,
    // controls from l to r
    output reg    PCEn, IorD, Memwrite, IRWrite, 
                  RegDst, MemtoReg, RegWrite, ALUsrcA,
    output reg [1 : 0] ALUsrcB, 
    output reg [2 : 0] ALUControl,
    output reg PCsrc
);
    // opcodes
    localparam rType = 6'b000000,
               lw    = 6'b100011,
               sw    = 6'b101011,
               beq   = 6'b000100;

    // funct fields
    localparam add = 6'b100000,
               sub = 6'b100010;

    // states
    localparam fetch     = 0,
               decode    = 1,
               execute1  = 2,
               execute2  = 3,
               execute3  = 4, // at most 3 cycles
               writeBack = 5;
    

    reg [2 : 0] currState, nextState;
    always @(negedge clk, posedge rst)begin
        if(rst)currState <= 0;
        else currState <= nextState;
    end

    always @(*) begin
        // next state compute, edit for all instructions
        case (currState)
            fetch : nextState <= decode;
            decode : nextState <= execute1;
            execute1 :begin
                case (opcode)
                    lw:nextState <= execute2;
                    rType:nextState <= execute2;
                    beq: nextState <= fetch;
                    default: nextState <= fetch;
                endcase

            end
            execute2 : begin
                case (opcode)
                    lw : nextState <= execute3; 
                    rType : nextState <= fetch;
                    default: nextState <= fetch;
                endcase
            end 
            execute3:nextState <= fetch;
            default: nextState <= fetch;
        endcase

        // output compute
        casez (currState)
            fetch : begin
                // writes
                Memwrite  = 0;
                RegWrite  = 0;
                IRWrite   = 1;
                PCEn      = 1;
                // muxes
                IorD      = 0;
                RegDst    = 0;
                MemtoReg  = 0;
                ALUsrcA   = 0;
                ALUsrcB   = 1;
                ALUControl= 2;
                PCsrc     = 0;
            end 

            decode : begin
                // writes
                Memwrite  = 0;
                RegWrite  = 0;
                IRWrite   = 0;
                PCEn      = 0;
                // muxes
                IorD      = 0;
                RegDst    = 0;
                MemtoReg  = 0;
                ALUsrcA   = 0;
                ALUsrcB   = 3;
                ALUControl= 2;
                PCsrc     = 0;            
            end

            execute1: begin
                case (opcode)
                    lw : begin
                        // writes
                        Memwrite  = 0;
                        RegWrite  = 0;
                        IRWrite   = 0;
                        PCEn      = 0;
                        // muxes
                        IorD      = 0;
                        RegDst    = 0;
                        MemtoReg  = 0;
                        ALUsrcA   = 1;
                        ALUsrcB   = 2;
                        ALUControl= 2;
                        PCsrc     = 0;
                    end 
                    rType: begin
                        // writes
                        Memwrite  = 0;
                        RegWrite  = 0;
                        IRWrite   = 0;
                        PCEn      = 0;
                        // muxes
                        IorD      = 0;
                        RegDst    = 0;
                        MemtoReg  = 0;
                        ALUsrcA   = 1;
                        ALUsrcB   = 0;
                        PCsrc     = 0;
                        case (funct)
                            add : ALUControl = 2;
                            sub : ALUControl = 6;
                            default: ALUControl = 2;
                        endcase
                    end
                    beq :begin
                        // writes
                        Memwrite  = 0;
                        RegWrite  = 0;
                        IRWrite   = 0;
                        PCEn      = zero;
                        // muxes
                        IorD      = 0;
                        RegDst    = 0;
                        MemtoReg  = 0;
                        ALUsrcA   = 1;
                        ALUsrcB   = 0;
                        ALUControl= 6;
                        PCsrc     = 1;
                    end
                    default: PCsrc = 0; // invalid instruction
                endcase
            end

            execute2: begin
                case (opcode)
                        lw: begin
                            // writes
                            Memwrite  = 0;
                            RegWrite  = 0;
                            IRWrite   = 0;
                            PCEn      = 0;
                            // muxes
                            IorD      = 1;
                            RegDst    = 0;
                            MemtoReg  = 0;
                            ALUsrcA   = 0;
                            ALUsrcB   = 0;
                            ALUControl= 0;
                            PCsrc     = 0;
                        end
                        rType: begin
                            // writes
                            Memwrite  = 0;
                            RegWrite  = 1;
                            IRWrite   = 0;
                            PCEn      = 0;
                            // muxes
                            IorD      = 0;
                            RegDst    = 1;
                            MemtoReg  = 0;
                            ALUsrcA   = 0;
                            ALUsrcB   = 0;
                            ALUControl= 0;
                            PCsrc     = 0;
                        end
                    default: PCsrc = 0;
                endcase
            end

            execute3: begin
                case (opcode)
                    lw:begin
                        // writes
                        Memwrite  = 0;
                        RegWrite  = 1;
                        IRWrite   = 0;
                        PCEn      = 0;
                        // muxes
                        IorD      = 0;
                        RegDst    = 0;
                        MemtoReg  = 1;
                        ALUsrcA   = 0;
                        ALUsrcB   = 0;
                        ALUControl= 0;
                        PCsrc     = 0;
                    end
                    default: PCsrc = 0;
                endcase
            end            
            default: PCsrc = 0;
        endcase        
    end

endmodule


// TODO insert the don't cares instead of the dumb shit you did.

/*
    // writes
    Memwrite  = 0;
    RegWrite  = 0;
    IRWrite   = 1;
    PCEn      = 1;
    // muxes
    IorD      = 0;
    RegDst    = 0;
    MemtoReg  = 0;
    ALUsrcA   = 0;
    ALUsrcB   = 1;
    ALUControl= 2;
    PCsrc     = 0;
*/

mips.v
`include "control_unit.v"
`include "data_path.v"

module MIPS(input clk, rst,
            input [4 : 0] addressTest);

    wire [5 : 0] opcode, funct;
    wire         PCEn, IorD, Memwrite, IRWrite, RegDst, MemtoReg, RegWrite, ALUsrcA,PCsrc, zero;
    wire [1 : 0] ALUsrcB;
    wire [2 : 0] ALUControl;

    controller cu(.clk(clk), .rst(rst), .opcode(opcode), .funct(funct), .PCEn(PCEn), .IorD(IorD), 
                .Memwrite(Memwrite), .IRWrite(IRWrite), .RegDst(RegDst), .MemtoReg(MemtoReg), .RegWrite(RegWrite),
                .ALUsrcA(ALUsrcA),.PCsrc(PCsrc), .ALUsrcB(ALUsrcB), .ALUControl(ALUControl), .zero(zero));

    dataPath   dp(.rst(rst), .clk(clk), .PCEn(PCEn), .IorD(IorD), .Memwrite(Memwrite),
                  .IRWrite(IRWrite), . RegDst( RegDst), .MemtoReg(MemtoReg), .RegWrite(RegWrite),
                  .ALUsrcA(ALUsrcA), .ALUsrcB(ALUsrcB), . ALUControl( ALUControl), .PCsrc(PCsrc), 
                  .addressTest(addressTest), .opcode(opcode), .funct(funct), .zero(zero)); 
endmodule

mips_testbench.v
`include "mips.v"
`timescale 1ns/1ps
module tb;

    reg clk, rst;
    reg [4 : 0] addressTest;

    MIPS d(clk, rst, addressTest);

    always #10 clk ^= 1;

    initial begin
        $dumpfile("mips_testbench.vcd");
        $dumpvars(0, tb);
        clk = 0;

        rst = 1;
        #5;
        rst = 0;

        addressTest = 10;
        #200;
        $finish;
    end

endmodule

mips_testbench.vcd
$date
	Fri Jul  5 19:26:31 2024
$end
$version
	Icarus Verilog
$end
$timescale
	1ps
$end
$scope module tb $end
$var reg 5 ! addressTest [4:0] $end
$var reg 1 " clk $end
$var reg 1 # rst $end
$scope module d $end
$var wire 5 $ addressTest [4:0] $end
$var wire 1 " clk $end
$var wire 1 # rst $end
$var wire 1 % zero $end
$var wire 6 & opcode [5:0] $end
$var wire 6 ' funct [5:0] $end
$var wire 1 ( RegWrite $end
$var wire 1 ) RegDst $end
$var wire 1 * PCsrc $end
$var wire 1 + PCEn $end
$var wire 1 , Memwrite $end
$var wire 1 - MemtoReg $end
$var wire 1 . IorD $end
$var wire 1 / IRWrite $end
$var wire 2 0 ALUsrcB [1:0] $end
$var wire 1 1 ALUsrcA $end
$var wire 3 2 ALUControl [2:0] $end
$scope module cu $end
$var wire 1 " clk $end
$var wire 1 # rst $end
$var wire 1 % zero $end
$var wire 6 3 opcode [5:0] $end
$var wire 6 4 funct [5:0] $end
$var parameter 6 5 add $end
$var parameter 6 6 beq $end
$var parameter 32 7 decode $end
$var parameter 32 8 execute1 $end
$var parameter 32 9 execute2 $end
$var parameter 32 : execute3 $end
$var parameter 32 ; fetch $end
$var parameter 6 < lw $end
$var parameter 6 = rType $end
$var parameter 6 > sub $end
$var parameter 6 ? sw $end
$var parameter 32 @ writeBack $end
$var reg 3 A ALUControl [2:0] $end
$var reg 1 1 ALUsrcA $end
$var reg 2 B ALUsrcB [1:0] $end
$var reg 1 / IRWrite $end
$var reg 1 . IorD $end
$var reg 1 - MemtoReg $end
$var reg 1 , Memwrite $end
$var reg 1 + PCEn $end
$var reg 1 * PCsrc $end
$var reg 1 ) RegDst $end
$var reg 1 ( RegWrite $end
$var reg 3 C currState [2:0] $end
$var reg 3 D nextState [2:0] $end
$upscope $end
$scope module dp $end
$var wire 3 E ALUControl [2:0] $end
$var wire 1 1 ALUsrcA $end
$var wire 2 F ALUsrcB [1:0] $end
$var wire 1 / IRWrite $end
$var wire 1 . IorD $end
$var wire 1 - MemtoReg $end
$var wire 1 , Memwrite $end
$var wire 1 + PCEn $end
$var wire 1 * PCsrc $end
$var wire 1 ) RegDst $end
$var wire 1 ( RegWrite $end
$var wire 5 G addressTest [4:0] $end
$var wire 1 " clk $end
$var wire 1 # rst $end
$var wire 1 % zero $end
$var wire 32 H outputTest [31:0] $end
$var wire 6 I opcode [5:0] $end
$var wire 6 J funct [5:0] $end
$var wire 32 K dataOutput [31:0] $end
$var wire 32 L btmp [31:0] $end
$var wire 32 M atmp [31:0] $end
$var wire 32 N SignImm [31:0] $end
$var wire 32 O RwriteData [31:0] $end
$var wire 5 P Radr [4:0] $end
$var wire 32 Q PCPrime [31:0] $end
$var wire 32 R PC [31:0] $end
$var wire 32 S Adr [31:0] $end
$var wire 32 T ALUResult [31:0] $end
$var reg 32 U A [31:0] $end
$var reg 32 V ALUOut [31:0] $end
$var reg 32 W B [31:0] $end
$var reg 32 X Data [31:0] $end
$var reg 32 Y Instr [31:0] $end
$var reg 32 Z SrcA [31:0] $end
$var reg 32 [ SrcB [31:0] $end
$scope module a $end
$var wire 3 \ ALUControl [2:0] $end
$var wire 32 ] SrcA [31:0] $end
$var wire 32 ^ SrcB [31:0] $end
$var parameter 3 _ add $end
$var parameter 3 ` andd $end
$var parameter 3 a orr $end
$var parameter 3 b slt $end
$var parameter 3 c sub $end
$var reg 32 d ALUResult [31:0] $end
$upscope $end
$scope module m $end
$var wire 32 e address [31:0] $end
$var wire 1 " clk $end
$var wire 32 f dataOutput [31:0] $end
$var wire 32 g dataWrite [31:0] $end
$var wire 1 # rst $end
$var wire 1 , writeEnable $end
$var integer 32 h i [31:0] $end
$upscope $end
$scope module p $end
$var wire 1 " clk $end
$var wire 32 i dataInput [31:0] $end
$var wire 1 + en $end
$var wire 1 # rst $end
$var reg 32 j dataOutput [31:0] $end
$upscope $end
$scope module r $end
$var wire 5 k addressA [4:0] $end
$var wire 5 l addressB [4:0] $end
$var wire 5 m addressTest [4:0] $end
$var wire 5 n addressWrite [4:0] $end
$var wire 1 " clk $end
$var wire 32 o dataWrite [31:0] $end
$var wire 1 # rst $end
$var wire 1 ( writeEnable $end
$var reg 32 p dataA [31:0] $end
$var reg 32 q dataB [31:0] $end
$var reg 32 r outputTest [31:0] $end
$var integer 32 s i [31:0] $end
$upscope $end
$upscope $end
$upscope $end
$upscope $end
$enddefinitions $end
$comment Show the parameter values. $end
$dumpall
b110 c
b111 b
b1 a
b0 `
b10 _
b101 @
b101011 ?
b100010 >
b0 =
b100011 <
b0 ;
b100 :
b11 9
b10 8
b1 7
b100 6
b100000 5
$end
#0
$dumpvars
b10100 s
bx r
bx q
bx p
bx o
bx n
bx m
bx l
bx k
b0 j
b1 i
b10000000000 h
bx g
b10001100000010100000000000100000 f
b0 e
b1 d
b1 ^
b0 ]
b10 \
b1 [
b0 Z
bx Y
bx X
bx W
bx V
bx U
b1 T
b0 S
b0 R
b1 Q
bx P
bx O
bx N
bx M
bx L
b10001100000010100000000000100000 K
bx J
bx I
bx H
bx G
b1 F
b10 E
b1 D
b0 C
b1 B
b10 A
bx 4
bx 3
b10 2
01
b1 0
1/
0.
0-
0,
1+
0*
0)
0(
bx '
bx &
0%
bx $
1#
0"
bx !
$end
#5000
b0 H
b0 r
b1010 !
b1010 $
b1010 G
b1010 m
0#
#10000
b10 Q
b10 i
b1010 P
b1010 n
b0 L
b0 q
b0 M
b0 p
b10 T
b10 d
b100011 &
b100011 3
b100011 I
b100000 '
b100000 4
b100000 J
b100000 N
b0 k
b1010 l
b1 O
b1 o
b10001010010100000000000000011 K
b10001010010100000000000000011 f
b1 S
b1 e
b1 Z
b1 ]
b10001100000010100000000000100000 Y
b10001100000010100000000000100000 X
b1 V
b1 R
b1 j
1"
#20000
b10 D
b100001 Q
b100001 i
b100001 T
b100001 d
b100000 [
b100000 ^
b11 0
b11 B
b11 F
0+
0/
b1 C
0"
#30000
b100001 O
b100001 o
b0 W
b0 g
b0 U
b100001 V
b10001010010100000000000000011 X
1"
#40000
b11 D
b100000 Q
b100000 i
b100000 T
b100000 d
b0 Z
b0 ]
b10 0
b10 B
b10 F
11
b10 C
0"
#50000
b100000 O
b100000 o
b100000 V
1"
#60000
b100 D
b0 Q
b0 i
1%
b0 T
b0 d
b0 [
b0 ^
b1 Z
b1 ]
b101 K
b101 f
b100000 S
b100000 e
b0 2
b0 A
b0 E
b0 \
b0 0
b0 B
b0 F
01
1.
b11 C
0"
#70000
b10001100000010100000000000100000 K
b10001100000010100000000000100000 f
b0 S
b0 e
b0 O
b0 o
b0 V
b101 X
1"
#80000
b0 D
b101 O
b101 o
b10001010010100000000000000011 K
b10001010010100000000000000011 f
b1 S
b1 e
1-
0.
1(
b100 C
0"
#90000
b10001010010100000000000000011 O
b10001010010100000000000000011 o
b10001010010100000000000000011 X
b101 L
b101 q
b101 H
b101 r
1"
#100000
b1 D
b10 Q
b10 i
0%
b10 T
b10 d
b1 [
b1 ^
b0 O
b0 o
b10 2
b10 A
b10 E
b10 \
b1 0
b1 B
b1 F
0-
1+
1/
0(
b0 C
0"
#110000
b11 Q
b11 i
b101 M
b101 p
b11 T
b11 d
b10 O
b10 o
b100 &
b100 3
b100 I
b11 '
b11 4
b11 J
b11 N
b1010 k
b0 K
b0 f
b10 S
b10 e
b10 Z
b10 ]
b101 W
b101 g
b10 V
b10001010010100000000000000011 Y
b10 R
b10 j
1"
#120000
b10 D
b101 Q
b101 i
b101 T
b101 d
b11 [
b11 ^
b11 0
b11 B
b11 F
0+
0/
b1 C
0"
#130000
b101 O
b101 o
b0 X
b101 V
b101 U
1"
#140000
b0 D
1+
1%
b0 T
b0 d
b101 [
b101 ^
b101 Z
b101 ]
1*
b110 2
b110 A
b110 E
b110 \
b0 0
b0 B
b0 F
11
b10 C
0"
#150000
b0 Q
b0 i
b0 O
b0 o
b10100010100101000000100000 K
b10100010100101000000100000 f
b101 S
b101 e
b0 V
b101 R
b101 j
1"
#160000
b1 D
b110 Q
b110 i
0%
b110 T
b110 d
b1 [
b1 ^
0*
b10 2
b10 A
b10 E
b10 \
b1 0
b1 B
b1 F
01
1/
b0 C
0"
#170000
b111 Q
b111 i
b1010 M
b1010 p
b111 T
b111 d
b0 &
b0 3
b0 I
b100000 '
b100000 4
b100000 J
b101000000100000 N
b10100 k
b110 O
b110 o
b0 K
b0 f
b110 S
b110 e
b110 Z
b110 ]
b10100010100101000000100000 Y
b10100010100101000000100000 X
b110 V
b110 R
b110 j
1"
#180000
b10 D
b101000000100110 Q
b101000000100110 i
b101000000100110 T
b101000000100110 d
b101000000100000 [
b101000000100000 ^
b11 0
b11 B
b11 F
0+
0/
b1 C
0"
#190000
b101000000100110 O
b101000000100110 o
b1010 U
b101000000100110 V
b0 X
1"
#200000
b11 D
b1111 Q
b1111 i
b1111 T
b1111 d
b101 [
b101 ^
b1010 Z
b1010 ]
b0 0
b0 B
b0 F
11
b10 C
0"
#210000
b1111 O
b1111 o
b1111 V
1"
#220000
b0 D
b100 Q
b100 i
b100 T
b100 d
b110 Z
b110 ]
b0 2
b0 A
b0 E
b0 \
01
1)
1(
b11 C
0"
#230000
b100 O
b100 o
b100 V
b1111 L
b1111 q
b1111 H
b1111 r
1"
#240000
b1 D
b111 Q
b111 i
b111 T
b111 d
b1 [
b1 ^
b10 2
b10 A
b10 E
b10 \
b1 0
b1 B
b1 F
0)
1+
1/
0(
b0 C
0"
#250000
b1000 Q
b1000 i
b0 P
b0 n
b0 L
b0 q
b0 M
b0 p
b1000 T
b1000 d
b0 '
b0 4
b0 J
b0 N
b0 k
b0 l
b111 O
b111 o
b111 S
b111 e
b111 Z
b111 ]
b0 Y
b111 V
b1111 W
b1111 g
b111 R
b111 j
1"
#260000
b10 D
b111 Q
b111 i
b111 T
b111 d
b0 [
b0 ^
b11 0
b11 B
b11 F
0+
0/
b1 C
0"
#270000
b0 W
b0 g
b0 U
1"
#280000
b11 D
b0 Q
b0 i
1%
b0 T
b0 d
b0 Z
b0 ]
b0 0
b0 B
b0 F
11
b10 C
0"
#290000
b0 O
b0 o
b0 V
1"
#300000
b0 D
b111 Z
b111 ]
b0 2
b0 A
b0 E
b0 \
01
1)
1(
b11 C
0"
