ALU/oneBAdder/singleBAdder.v

module oneBAdder (
    input a, input b, input cIn, output s, output cOut
);
assign s = a ^ b ^ cIn;
assign cOut = (a & b) | (cIn & (a ^ b));
endmodule

ALU/alu.v
`include "oneBAdder/singleBAdder.v"
`define N 16 // I don't like parameters

/*
+--------+--------+
| OPCODE | Result |
+--------+--------+
| 0      | a + b  |
| 1      | a - b  |
| 2      | a & b  |
| 3      | a | b  |
| 4      | a ^ b  |
| 5      | a > b  |
| 6      | a << 1 |
| 7      | a >> 1 |
+--------+--------+
sign     = ovf ^ N     // the true sign
negative = s[`N - 1]   // hardwired to the sign bit
ovf      = s & !a & !b | !s & a & b = cin ^ cout
*/

module ALU(input [2 : 0] OPCODE, input [`N - 1 : 0]a, input [`N - 1 : 0] b, output reg [`N - 1 : 0] s, output cOut, output ovf, output sign, output negative);

    wire[`N - 1 : 0] andOut, orOut, xorOut, shiftrOut, shiftlOut, gtOut, addOut;
    wire [`N : 0] tmp_carry; // 0 1 .. N, tmp_carry[N] is cout.
    wire caryyInLastAdder;

    assign ovf = tmp_carry[`N] ^ tmp_carry[`N - 1];
    assign tmp_carry[0] = OPCODE[0]; // OPCODE & 0x1
    assign cOut = tmp_carry[`N];
    assign negative = addOut[`N - 1]; 
    assign sign = ovf ^ negative;
    genvar i;
    generate
        for(i = 0;i < `N;i = i + 1)begin : NbitAdder
            oneBAdder aa(
                .a(a[i]),
                .b(b[i] ^ OPCODE[0]), 
                .cIn(tmp_carry[i]),
                .cOut(tmp_carry[i + 1]),
                .s(addOut[i])
            );
        end
    endgenerate
    assign andOut = a & b;
    assign orOut = a | b;
    assign xorOut = a ^ b;
    assign shiftrOut = a >> 1;
    assign shiftlOut = a << 1;
    assign gtOut = a > b ? 1 : 0;
    always @(*) begin
        case (OPCODE)
            0, 1: s = addOut;
            2   : s = andOut;
            3   : s = orOut;
            4   : s = xorOut;
            5   : s = gtOut;
            6   : s = shiftlOut;
            7   : s = shiftrOut;
            default : s = 0;
        endcase
    end

endmodule

ALU/test.v
`include "alu.v"
`timescale 1ns/1ns



module test;
    reg [2 : 0] opcodeTest;
    reg [`N - 1 : 0]firstOperandTest, secondOperandTest;
    wire[`N - 1 : 0] resultTest;
    wire carryOut;
    ALU DUT(
        .OPCODE(opcodeTest),
        .a(firstOperandTest),
        .b(secondOperandTest),
        .cOut(carryOut),
        .s(resultTest)
    );

    wire result;
    integer opcode, firstOperand, secondOperand;
    initial begin
        $dumpfile("test.vcd");
        $dumpvars(0, test);
        for(opcode = 0;opcode < 8;opcode = opcode + 1)begin
            for(firstOperand = 0;firstOperand < 8;firstOperand = firstOperand + 1)begin
                for(secondOperand = 0;secondOperand < 8;secondOperand = secondOperand + 1)begin
                    opcodeTest = opcode; firstOperandTest = firstOperand; secondOperandTest = secondOperand;
                    opcodeTest = opcode;
                    #10;
                end
            end
        end
        #10
        opcodeTest = 0;
        firstOperandTest = 32767;
        secondOperandTest = 5;
        #10
        $finish;
    end

endmodule

ALU/test.vcd
$date
	Sun Jun 16 12:36:47 2024
$end
$version
	Icarus Verilog
$end
$timescale
	1ns
$end
$scope module test $end
$var wire 16 ! resultTest [15:0] $end
$var wire 1 " carryOut $end
$var reg 16 # firstOperandTest [15:0] $end
$var reg 3 $ opcodeTest [2:0] $end
$var reg 16 % secondOperandTest [15:0] $end
$var integer 32 & firstOperand [31:0] $end
$var integer 32 ' opcode [31:0] $end
$var integer 32 ( secondOperand [31:0] $end
$scope module DUT $end
$var wire 3 ) OPCODE [2:0] $end
$var wire 16 * a [15:0] $end
$var wire 16 + andOut [15:0] $end
$var wire 16 , b [15:0] $end
$var wire 16 - orOut [15:0] $end
$var wire 1 . ovf $end
$var wire 1 / sign $end
$var wire 16 0 xorOut [15:0] $end
$var wire 17 1 tmp_carry [16:0] $end
$var wire 16 2 shiftrOut [15:0] $end
$var wire 16 3 shiftlOut [15:0] $end
$var wire 1 4 negative $end
$var wire 16 5 gtOut [15:0] $end
$var wire 1 " cOut $end
$var wire 16 6 addOut [15:0] $end
$var reg 16 7 s [15:0] $end
$scope begin NbitAdder[0] $end
$var parameter 2 8 i $end
$scope module aa $end
$var wire 1 9 a $end
$var wire 1 : b $end
$var wire 1 ; cIn $end
$var wire 1 < cOut $end
$var wire 1 = s $end
$upscope $end
$upscope $end
$scope begin NbitAdder[1] $end
$var parameter 2 > i $end
$scope module aa $end
$var wire 1 ? a $end
$var wire 1 @ b $end
$var wire 1 A cIn $end
$var wire 1 B cOut $end
$var wire 1 C s $end
$upscope $end
$upscope $end
$scope begin NbitAdder[2] $end
$var parameter 3 D i $end
$scope module aa $end
$var wire 1 E a $end
$var wire 1 F b $end
$var wire 1 G cIn $end
$var wire 1 H cOut $end
$var wire 1 I s $end
$upscope $end
$upscope $end
$scope begin NbitAdder[3] $end
$var parameter 3 J i $end
$scope module aa $end
$var wire 1 K a $end
$var wire 1 L b $end
$var wire 1 M cIn $end
$var wire 1 N cOut $end
$var wire 1 O s $end
$upscope $end
$upscope $end
$scope begin NbitAdder[4] $end
$var parameter 4 P i $end
$scope module aa $end
$var wire 1 Q a $end
$var wire 1 R b $end
$var wire 1 S cIn $end
$var wire 1 T cOut $end
$var wire 1 U s $end
$upscope $end
$upscope $end
$scope begin NbitAdder[5] $end
$var parameter 4 V i $end
$scope module aa $end
$var wire 1 W a $end
$var wire 1 X b $end
$var wire 1 Y cIn $end
$var wire 1 Z cOut $end
$var wire 1 [ s $end
$upscope $end
$upscope $end
$scope begin NbitAdder[6] $end
$var parameter 4 \ i $end
$scope module aa $end
$var wire 1 ] a $end
$var wire 1 ^ b $end
$var wire 1 _ cIn $end
$var wire 1 ` cOut $end
$var wire 1 a s $end
$upscope $end
$upscope $end
$scope begin NbitAdder[7] $end
$var parameter 4 b i $end
$scope module aa $end
$var wire 1 c a $end
$var wire 1 d b $end
$var wire 1 e cIn $end
$var wire 1 f cOut $end
$var wire 1 g s $end
$upscope $end
$upscope $end
$scope begin NbitAdder[8] $end
$var parameter 5 h i $end
$scope module aa $end
$var wire 1 i a $end
$var wire 1 j b $end
$var wire 1 k cIn $end
$var wire 1 l cOut $end
$var wire 1 m s $end
$upscope $end
$upscope $end
$scope begin NbitAdder[9] $end
$var parameter 5 n i $end
$scope module aa $end
$var wire 1 o a $end
$var wire 1 p b $end
$var wire 1 q cIn $end
$var wire 1 r cOut $end
$var wire 1 s s $end
$upscope $end
$upscope $end
$scope begin NbitAdder[10] $end
$var parameter 5 t i $end
$scope module aa $end
$var wire 1 u a $end
$var wire 1 v b $end
$var wire 1 w cIn $end
$var wire 1 x cOut $end
$var wire 1 y s $end
$upscope $end
$upscope $end
$scope begin NbitAdder[11] $end
$var parameter 5 z i $end
$scope module aa $end
$var wire 1 { a $end
$var wire 1 | b $end
$var wire 1 } cIn $end
$var wire 1 ~ cOut $end
$var wire 1 !" s $end
$upscope $end
$upscope $end
$scope begin NbitAdder[12] $end
$var parameter 5 "" i $end
$scope module aa $end
$var wire 1 #" a $end
$var wire 1 $" b $end
$var wire 1 %" cIn $end
$var wire 1 &" cOut $end
$var wire 1 '" s $end
$upscope $end
$upscope $end
$scope begin NbitAdder[13] $end
$var parameter 5 (" i $end
$scope module aa $end
$var wire 1 )" a $end
$var wire 1 *" b $end
$var wire 1 +" cIn $end
$var wire 1 ," cOut $end
$var wire 1 -" s $end
$upscope $end
$upscope $end
$scope begin NbitAdder[14] $end
$var parameter 5 ." i $end
$scope module aa $end
$var wire 1 /" a $end
$var wire 1 0" b $end
$var wire 1 1" cIn $end
$var wire 1 2" cOut $end
$var wire 1 3" s $end
$upscope $end
$upscope $end
$scope begin NbitAdder[15] $end
$var parameter 5 4" i $end
$scope module aa $end
$var wire 1 5" a $end
$var wire 1 6" b $end
$var wire 1 7" cIn $end
$var wire 1 8" cOut $end
$var wire 1 9" s $end
$upscope $end
$upscope $end
$upscope $end
$upscope $end
$enddefinitions $end
$comment Show the parameter values. $end
$dumpall
b1111 4"
b1110 ."
b1101 ("
b1100 ""
b1011 z
b1010 t
b1001 n
b1000 h
b111 b
b110 \
b101 V
b100 P
b11 J
b10 D
b1 >
b0 8
$end
#0
$dumpvars
09"
08"
07"
06"
05"
03"
02"
01"
00"
0/"
0-"
0,"
0+"
0*"
0)"
0'"
0&"
0%"
0$"
0#"
0!"
0~
0}
0|
0{
0y
0x
0w
0v
0u
0s
0r
0q
0p
0o
0m
0l
0k
0j
0i
0g
0f
0e
0d
0c
0a
0`
0_
0^
0]
0[
0Z
0Y
0X
0W
0U
0T
0S
0R
0Q
0O
0N
0M
0L
0K
0I
0H
0G
0F
0E
0C
0B
0A
0@
0?
0=
0<
0;
0:
09
b0 7
b0 6
b0 5
04
b0 3
b0 2
b0 1
b0 0
0/
0.
b0 -
b0 ,
b0 +
b0 *
b0 )
b0 (
b0 '
b0 &
b0 %
b0 $
b0 #
0"
b0 !
$end
#10
b1 !
b1 7
b1 6
1=
1:
b1 -
b1 0
b1 %
b1 ,
b1 (
#20
b10 !
b10 7
0=
b10 6
1C
0:
1@
b10 -
b10 0
b10 %
b10 ,
b10 (
#30
b11 !
b11 7
b11 6
1=
1:
b11 -
b11 0
b11 %
b11 ,
b11 (
#40
b100 !
b100 7
0=
0C
b100 6
1I
0:
0@
1F
b100 -
b100 0
b100 %
b100 ,
b100 (
#50
b101 !
b101 7
b101 6
1=
1:
b101 -
b101 0
b101 %
b101 ,
b101 (
#60
b110 !
b110 7
0=
b110 6
1C
0:
1@
b110 -
b110 0
b110 %
b110 ,
b110 (
#70
b111 !
b111 7
b111 6
1=
1:
b111 -
b111 0
b111 %
b111 ,
b111 (
#80
0C
0I
b1 !
b1 7
0A
b1 6
1=
b0 1
0<
0:
0@
0F
b1 5
b1 -
b1 0
19
b10 3
b0 %
b0 ,
b1 #
b1 *
b1 &
b0 (
#90
1C
b10 !
b10 7
1A
b10 6
0=
b10 1
1<
1:
b1 +
b0 0
b0 5
b1 %
b1 ,
b1 (
#100
0I
0G
0A
b11 !
b11 7
0B
1=
b0 1
0<
b11 6
1C
0:
1@
b0 +
b11 -
b11 0
b10 %
b10 ,
b10 (
#110
1I
1G
1B
0C
b100 !
b100 7
1A
b100 6
0=
b110 1
1<
1:
b1 +
b10 0
b11 %
b11 ,
b11 (
#120
0O
0G
0M
0A
0B
b101 !
b101 7
0H
1=
b0 1
0<
0C
b101 6
1I
0:
0@
1F
b0 +
b101 -
b101 0
b100 %
b100 ,
b100 (
#130
1C
b110 !
b110 7
1A
b110 6
0=
b10 1
1<
1:
b1 +
b100 0
b101 %
b101 ,
b101 (
#140
0O
0M
0H
1I
0G
0A
b111 !
b111 7
0B
1=
b0 1
0<
b111 6
1C
0:
1@
b0 +
b111 -
b111 0
b110 %
b110 ,
b110 (
#150
1O
1M
1H
0I
1G
1B
0C
b1000 !
b1000 7
1A
b1000 6
0=
b1110 1
1<
1:
b1 +
b110 0
b111 %
b111 ,
b111 (
#160
0O
0M
0G
0H
0B
0I
0A
b10 !
b10 7
0=
b0 1
0<
b10 6
1C
0:
0@
0F
b1 5
b0 +
b10 -
b10 0
09
1?
b1 2
b100 3
b0 %
b0 ,
b10 #
b10 *
b10 &
b0 (
#170
b11 !
b11 7
b11 6
1=
1:
b11 -
b11 0
b1 %
b1 ,
b1 (
#180
1I
b100 !
b100 7
1G
0=
b100 6
0C
b100 1
1B
0:
1@
b10 +
b10 -
b0 0
b0 5
b10 %
b10 ,
b10 (
#190
b101 !
b101 7
b101 6
1=
1:
b11 -
b1 0
b11 %
b11 ,
b11 (
#200
0O
0M
0G
b110 !
b110 7
0H
0=
1C
b0 1
0B
b110 6
1I
0:
0@
1F
b0 +
b110 -
b110 0
b100 %
b100 ,
b100 (
#210
b111 !
b111 7
b111 6
1=
1:
b111 -
b111 0
b101 %
b101 ,
b101 (
#220
1O
1M
1H
0I
b1000 !
b1000 7
1G
0=
b1000 6
0C
b1100 1
1B
0:
1@
b10 +
b110 -
b100 0
b110 %
b110 ,
b110 (
#230
b1001 !
b1001 7
b1001 6
1=
1:
b111 -
b101 0
b111 %
b111 ,
b111 (
#240
0G
0B
0O
1C
0M
0H
0I
b11 !
b11 7
0A
b11 6
1=
b0 1
0<
0:
0@
0F
b1 5
b0 +
b11 -
b11 0
19
b110 3
b0 %
b0 ,
b11 #
b11 *
b11 &
b0 (
#250
1I
1G
1B
0C
b100 !
b100 7
1A
b100 6
0=
b110 1
1<
1:
b1 +
b10 0
b1 %
b1 ,
b1 (
#260
0A
b101 !
b101 7
1=
b100 1
0<
b101 6
0C
0:
1@
b10 +
b1 0
b10 %
b10 ,
b10 (
#270
1C
b110 !
b110 7
1A
b110 6
0=
b110 1
1<
1:
b11 +
b0 0
b0 5
b11 %
b11 ,
b11 (
#280
0G
0B
0O
0M
0A
b111 !
b111 7
0H
1=
b0 1
0<
1C
b111 6
1I
0:
0@
1F
b0 +
b111 -
b111 0
b100 %
b100 ,
b100 (
#290
1O
1M
1H
0I
1G
1B
0C
b1000 !
b1000 7
1A
b1000 6
0=
b1110 1
1<
1:
b1 +
b110 0
b101 %
b101 ,
b101 (
#300
0A
b1001 !
b1001 7
1=
b1100 1
0<
b1001 6
0C
0:
1@
b10 +
b101 0
b110 %
b110 ,
b110 (
#310
1C
b1010 !
b1010 7
1A
b1010 6
0=
b1110 1
1<
1:
b11 +
b100 0
b111 %
b111 ,
b111 (
#320
0O
0M
0H
0G
0B
0A
b100 !
b100 7
0=
b0 1
0<
0C
b100 6
1I
0:
0@
0F
b1 5
b0 +
b100 -
09
0?
1E
b10 2
b1000 3
b0 %
b0 ,
b100 #
b100 *
b100 &
b0 (
#330
b101 !
b101 7
b101 6
1=
1:
b101 -
b101 0
b1 %
b1 ,
b1 (
#340
b110 !
b110 7
0=
b110 6
1C
0:
1@
b110 -
b110 0
b10 %
b10 ,
b10 (
#350
b111 !
b111 7
b111 6
1=
1:
b111 -
b111 0
b11 %
b11 ,
b11 (
#360
1O
b1000 !
b1000 7
1M
0=
0C
b1000 6
0I
b1000 1
1H
0:
0@
1F
b100 +
b100 -
b0 0
b0 5
b100 %
b100 ,
b100 (
#370
b1001 !
b1001 7
b1001 6
1=
1:
b101 -
b1 0
b101 %
b101 ,
b101 (
#380
b1010 !
b1010 7
0=
b1010 6
1C
0:
1@
b110 -
b10 0
b110 %
b110 ,
b110 (
#390
b1011 !
b1011 7
b1011 6
1=
1:
b111 -
b11 0
b111 %
b111 ,
b111 (
#400
0C
0O
0M
1I
0H
b101 !
b101 7
0A
b101 6
1=
b0 1
0<
0:
0@
0F
b1 5
b0 +
b101 -
b101 0
19
b1010 3
b0 %
b0 ,
b101 #
b101 *
b101 &
b0 (
#410
1C
b110 !
b110 7
1A
b110 6
0=
b10 1
1<
1:
b1 +
b100 0
b1 %
b1 ,
b1 (
#420
0O
0M
0H
1I
0G
0A
b111 !
b111 7
0B
1=
b0 1
0<
b111 6
1C
0:
1@
b0 +
b111 -
b111 0
b10 %
b10 ,
b10 (
#430
1O
1M
1H
0I
1G
1B
0C
b1000 !
b1000 7
1A
b1000 6
0=
b1110 1
1<
1:
b1 +
b110 0
b11 %
b11 ,
b11 (
#440
0G
0A
0B
b1001 !
b1001 7
1=
b1000 1
0<
0C
b1001 6
0I
0:
0@
1F
b100 +
b101 -
b1 0
b100 %
b100 ,
b100 (
#450
1C
b1010 !
b1010 7
1A
b1010 6
0=
b1010 1
1<
1:
b101 +
b0 0
b0 5
b101 %
b101 ,
b101 (
#460
0I
0G
0A
b1011 !
b1011 7
0B
1=
b1000 1
0<
b1011 6
1C
0:
1@
b100 +
b111 -
b11 0
b110 %
b110 ,
b110 (
#470
1I
1G
1B
0C
b1100 !
b1100 7
1A
b1100 6
0=
b1110 1
1<
1:
b101 +
b10 0
b111 %
b111 ,
b111 (
#480
0O
0M
0H
0G
0B
1I
0A
b110 !
b110 7
0=
b0 1
0<
b110 6
1C
0:
0@
0F
b1 5
b0 +
b110 -
b110 0
09
1?
b11 2
b1100 3
b0 %
b0 ,
b110 #
b110 *
b110 &
b0 (
#490
b111 !
b111 7
b111 6
1=
1:
b111 -
b111 0
b1 %
b1 ,
b1 (
#500
1O
1M
1H
0I
b1000 !
b1000 7
1G
0=
b1000 6
0C
b1100 1
1B
0:
1@
b10 +
b110 -
b100 0
b10 %
b10 ,
b10 (
#510
b1001 !
b1001 7
b1001 6
1=
1:
b111 -
b101 0
b11 %
b11 ,
b11 (
#520
0G
b1010 !
b1010 7
0=
1C
b1000 1
0B
b1010 6
0I
0:
0@
1F
b100 +
b110 -
b10 0
b100 %
b100 ,
b100 (
#530
b1011 !
b1011 7
b1011 6
1=
1:
b111 -
b11 0
b101 %
b101 ,
b101 (
#540
1I
b1100 !
b1100 7
1G
0=
b1100 6
0C
b1100 1
1B
0:
1@
b110 +
b110 -
b0 0
b0 5
b110 %
b110 ,
b110 (
#550
b1101 !
b1101 7
b1101 6
1=
1:
b111 -
b1 0
b111 %
b111 ,
b111 (
#560
0O
0M
0H
0G
0B
1C
1I
b111 !
b111 7
0A
b111 6
1=
b0 1
0<
0:
0@
0F
b1 5
b0 +
b111 0
19
b1110 3
b0 %
b0 ,
b111 #
b111 *
b111 &
b0 (
#570
1O
1M
1H
0I
1G
1B
0C
b1000 !
b1000 7
1A
b1000 6
0=
b1110 1
1<
1:
b1 +
b110 0
b1 %
b1 ,
b1 (
#580
0A
b1001 !
b1001 7
1=
b1100 1
0<
b1001 6
0C
0:
1@
b10 +
b101 0
b10 %
b10 ,
b10 (
#590
1C
b1010 !
b1010 7
1A
b1010 6
0=
b1110 1
1<
1:
b11 +
b100 0
b11 %
b11 ,
b11 (
#600
0G
0B
0A
b1011 !
b1011 7
1=
b1000 1
0<
1C
b1011 6
0I
0:
0@
1F
b100 +
b11 0
b100 %
b100 ,
b100 (
#610
1I
1G
1B
0C
b1100 !
b1100 7
1A
b1100 6
0=
b1110 1
1<
1:
b101 +
b10 0
b101 %
b101 ,
b101 (
#620
0A
b1101 !
b1101 7
1=
b1100 1
0<
b1101 6
0C
0:
1@
b110 +
b1 0
b110 %
b110 ,
b110 (
#630
1C
b1110 !
b1110 7
1A
b1110 6
0=
b1110 1
1<
1:
b111 +
b0 0
b0 5
b111 %
b111 ,
b111 (
#640
1"
18"
0.
17"
12"
11"
1,"
1+"
1&"
1%"
1~
1}
1x
1w
1r
1q
1l
1k
1f
1e
1`
1_
1Z
1Y
1T
1S
0/
1N
04
b0 !
b0 7
0O
0U
0[
0a
0g
0m
0s
0y
0!"
0'"
0-"
03"
09"
0C
b0 6
0I
1L
1R
1X
1^
1d
1j
1p
1v
1|
1$"
1*"
10"
16"
1;
b0 +
b0 -
09
0?
0E
b0 2
b0 3
b11111111111111111 1
b0 %
b0 ,
b0 #
b0 *
b1 $
b1 )
b1 '
b0 &
b0 (
#650
1/
0"
14
08"
0.
19"
07"
02"
13"
01"
0,"
1-"
0+"
0&"
1'"
0%"
0~
1!"
0}
0x
1y
0w
0r
1s
0q
0l
1m
0k
0f
1g
0e
0`
1a
0_
0Z
1[
0Y
0T
1U
0S
0N
1O
0M
0H
1I
0G
0B
1C
0A
b1111111111111111 !
b1111111111111111 7
b1 1
0<
b1111111111111111 6
1=
0:
b1 -
b1 0
b1 %
b1 ,
b1 (
#660
1A
b11 1
1<
b1111111111111110 !
b1111111111111110 7
0=
b1111111111111110 6
1C
1:
0@
b10 -
b10 0
b10 %
b10 ,
b10 (
#670
0C
0A
b1111111111111101 !
b1111111111111101 7
b1 1
0<
b1111111111111101 6
1=
0:
b11 -
b11 0
b11 %
b11 ,
b11 (
#680
1G
1B
1A
b111 1
1<
b1111111111111100 !
b1111111111111100 7
0=
0C
b1111111111111100 6
1I
1:
1@
0F
b100 -
b100 0
b100 %
b100 ,
b100 (
#690
0I
0G
0B
1C
0A
b1111111111111011 !
b1111111111111011 7
b1 1
0<
b1111111111111011 6
1=
0:
b101 -
b101 0
b101 %
b101 ,
b101 (
#700
1A
b11 1
1<
b1111111111111010 !
b1111111111111010 7
0=
b1111111111111010 6
1C
1:
0@
b110 -
b110 0
b110 %
b110 ,
b110 (
#710
0C
0A
b1111111111111001 !
b1111111111111001 7
b1 1
0<
b1111111111111001 6
1=
0:
b111 -
b111 0
b111 %
b111 ,
b111 (
#720
0/
1"
04
18"
0.
09"
17"
12"
03"
11"
1,"
0-"
1+"
1&"
0'"
1%"
1~
0!"
1}
1x
0y
1w
1r
0s
1q
1l
0m
1k
1f
0g
1e
1`
0a
1_
1Z
0[
1Y
1T
0U
1S
1N
0O
1M
1H
1G
1B
1A
0C
0I
b1 !
b1 7
b11111111111111111 1
1<
b1 6
1=
1:
1@
1F
b1 5
b1 -
b1 0
19
b10 3
b0 %
b0 ,
b1 #
b1 *
b1 &
b0 (
#730
b0 !
b0 7
b0 6
0=
0:
b1 +
b0 0
b0 5
b1 %
b1 ,
b1 (
#740
1/
0"
14
08"
0.
19"
07"
02"
13"
01"
0,"
1-"
0+"
0&"
1'"
0%"
0~
1!"
0}
0x
1y
0w
0r
1s
0q
0l
1m
0k
0f
1g
0e
0`
1a
0_
0Z
1[
0Y
0T
1U
0S
0N
1O
0M
0H
1I
0G
b1111111111111111 !
b1111111111111111 7
b11 1
0B
1=
b1111111111111111 6
1C
1:
0@
b0 +
b11 -
b11 0
b10 %
b10 ,
b10 (
#750
b1111111111111110 !
b1111111111111110 7
b1111111111111110 6
0=
0:
b1 +
b10 0
b11 %
b11 ,
b11 (
#760
1G
b111 1
1B
b1111111111111101 !
b1111111111111101 7
1=
0C
b1111111111111101 6
1I
1:
1@
0F
b0 +
b101 -
b101 0
b100 %
b100 ,
b100 (
#770
b1111111111111100 !
b1111111111111100 7
b1111111111111100 6
0=
0:
b1 +
b100 0
b101 %
b101 ,
b101 (
#780
0I
0G
b1111111111111011 !
b1111111111111011 7
b11 1
0B
1=
b1111111111111011 6
1C
1:
0@
b0 +
b111 -
b111 0
b110 %
b110 ,
b110 (
#790
b1111111111111010 !
b1111111111111010 7
b1111111111111010 6
0=
0:
b1 +
b110 0
b111 %
b111 ,
b111 (
#800
0/
1"
04
18"
0.
09"
17"
12"
03"
11"
1,"
0-"
1+"
1&"
0'"
1%"
1~
0!"
1}
1x
0y
1w
1r
0s
1q
1l
0m
1k
1f
0g
1e
1`
0a
1_
1Z
0[
1Y
1T
0U
1S
1N
0O
1M
1H
1A
1G
0I
1<
b10 !
b10 7
b11111111111111111 1
1B
0=
b10 6
1C
1:
1@
1F
b1 5
b0 +
b10 -
b10 0
09
1?
b1 2
b100 3
b0 %
b0 ,
b10 #
b10 *
b10 &
b0 (
#810
0C
0A
b1 !
b1 7
b11111111111111101 1
0<
b1 6
1=
0:
b11 -
b11 0
b1 %
b1 ,
b1 (
#820
0/
1"
04
18"
0.
09"
17"
12"
03"
11"
1,"
0-"
1+"
1&"
0'"
1%"
1~
0!"
1}
1x
0y
1w
1r
0s
1q
1l
0m
1k
1f
0g
1e
1`
0a
1_
1Z
0[
1Y
1T
0U
1S
1N
0O
1M
1H
1A
0I
1<
b0 !
b0 7
1G
0=
b0 6
0C
b11111111111111111 1
1B
1:
0@
b10 +
b10 -
b0 0
b0 5
b10 %
b10 ,
b10 (
#830
1/
0"
14
08"
0.
19"
07"
02"
13"
01"
0,"
1-"
0+"
0&"
1'"
0%"
0~
1!"
0}
0x
1y
0w
0r
1s
0q
0l
1m
0k
0f
1g
0e
0`
1a
0_
0Z
1[
0Y
0T
1U
0S
0N
1O
0M
0H
1I
0G
0B
1C
0A
b1111111111111111 !
b1111111111111111 7
b1 1
0<
b1111111111111111 6
1=
0:
b11 -
b1 0
b11 %
b11 ,
b11 (
#840
1A
1<
1G
b1111111111111110 !
b1111111111111110 7
0=
1C
b111 1
1B
b1111111111111110 6
1I
1:
1@
0F
b0 +
b110 -
b110 0
b100 %
b100 ,
b100 (
#850
0C
0A
b1111111111111101 !
b1111111111111101 7
b101 1
0<
b1111111111111101 6
1=
0:
b111 -
b111 0
b101 %
b101 ,
b101 (
#860
1A
1I
1<
b1111111111111100 !
b1111111111111100 7
1G
0=
b1111111111111100 6
0C
b111 1
1B
1:
0@
b10 +
b110 -
b100 0
b110 %
b110 ,
b110 (
#870
0I
0G
0B
1C
0A
b1111111111111011 !
b1111111111111011 7
b1 1
0<
b1111111111111011 6
1=
0:
b111 -
b101 0
b111 %
b111 ,
b111 (
#880
0/
1"
04
18"
0.
09"
17"
12"
03"
11"
1,"
0-"
1+"
1&"
0'"
1%"
1~
0!"
1}
1x
0y
1w
1r
0s
1q
1l
0m
1k
1f
0g
1e
1`
0a
1_
1Z
0[
1Y
1T
0U
1S
1N
0O
1M
1H
1G
1A
1C
1B
0I
b11 !
b11 7
b11111111111111111 1
1<
b11 6
1=
1:
1@
1F
b1 5
b0 +
b11 -
b11 0
19
b110 3
b0 %
b0 ,
b11 #
b11 *
b11 &
b0 (
#890
b10 !
b10 7
b10 6
0=
0:
b1 +
b10 0
b1 %
b1 ,
b1 (
#900
b1 !
b1 7
1=
b1 6
0C
1:
0@
b10 +
b1 0
b10 %
b10 ,
b10 (
#910
b0 !
b0 7
b0 6
0=
0:
b11 +
b0 0
b0 5
b11 %
b11 ,
b11 (
#920
1/
0"
14
08"
0.
19"
07"
02"
13"
01"
0,"
1-"
0+"
0&"
1'"
0%"
0~
1!"
0}
0x
1y
0w
0r
1s
0q
0l
1m
0k
0f
1g
0e
0`
1a
0_
0Z
1[
0Y
0T
1U
0S
0N
1O
0M
b1111111111111111 !
b1111111111111111 7
b111 1
0H
1=
1C
b1111111111111111 6
1I
1:
1@
0F
b0 +
b111 -
b111 0
b100 %
b100 ,
b100 (
#930
b1111111111111110 !
b1111111111111110 7
b1111111111111110 6
0=
0:
b1 +
b110 0
b101 %
b101 ,
b101 (
#940
b1111111111111101 !
b1111111111111101 7
1=
b1111111111111101 6
0C
1:
0@
b10 +
b101 0
b110 %
b110 ,
b110 (
#950
b1111111111111100 !
b1111111111111100 7
b1111111111111100 6
0=
0:
b11 +
b100 0
b111 %
b111 ,
b111 (
#960
0/
1"
04
18"
0.
09"
17"
12"
03"
11"
1,"
0-"
1+"
1&"
0'"
1%"
1~
0!"
1}
1x
0y
1w
1r
0s
1q
1l
0m
1k
1f
0g
1e
1`
0a
1_
1Z
0[
1Y
1T
0U
1S
1N
0O
1A
1G
1M
1<
1B
b100 !
b100 7
b11111111111111111 1
1H
0=
0C
b100 6
1I
1:
1@
1F
b1 5
b0 +
b100 -
09
0?
1E
b10 2
b1000 3
b0 %
b0 ,
b100 #
b100 *
b100 &
b0 (
#970
0I
0G
0B
1C
0A
b11 !
b11 7
b11111111111111001 1
0<
b11 6
1=
0:
b101 -
b101 0
b1 %
b1 ,
b1 (
#980
1A
b11111111111111011 1
1<
b10 !
b10 7
0=
b10 6
1C
1:
0@
b110 -
b110 0
b10 %
b10 ,
b10 (
#990
0C
0A
b1 !
b1 7
b11111111111111001 1
0<
b1 6
1=
0:
b111 -
b111 0
b11 %
b11 ,
b11 (
#1000
0/
1"
04
18"
0.
09"
17"
12"
03"
11"
1,"
0-"
1+"
1&"
0'"
1%"
1~
0!"
1}
1x
0y
1w
1r
0s
1q
1l
0m
1k
1f
0g
1e
1`
0a
1_
1Z
0[
1Y
1T
1G
0U
1B
1S
1N
1A
0O
1<
b0 !
b0 7
1M
0=
0C
b0 6
0I
b11111111111111111 1
1H
1:
1@
0F
b100 +
b100 -
b0 0
b0 5
b100 %
b100 ,
b100 (
#1010
1/
0"
14
08"
0.
19"
07"
02"
13"
01"
0,"
1-"
0+"
0&"
1'"
0%"
0~
1!"
0}
0x
1y
0w
0r
1s
0q
0l
1m
0k
0f
1g
0e
0`
1a
0_
0Z
1[
0Y
0T
1U
0S
0N
1O
0M
0H
1I
0G
0B
1C
0A
b1111111111111111 !
b1111111111111111 7
b1 1
0<
b1111111111111111 6
1=
0:
b101 -
b1 0
b101 %
b101 ,
b101 (
#1020
1A
b11 1
1<
b1111111111111110 !
b1111111111111110 7
0=
b1111111111111110 6
1C
1:
0@
b110 -
b10 0
b110 %
b110 ,
b110 (
#1030
0C
0A
b1111111111111101 !
b1111111111111101 7
b1 1
0<
b1111111111111101 6
1=
0:
b111 -
b11 0
b111 %
b111 ,
b111 (
#1040
0/
1"
04
18"
0.
09"
17"
12"
03"
11"
1,"
0-"
1+"
1&"
0'"
1%"
1~
0!"
1}
1x
0y
1w
1r
0s
1q
1l
0m
1k
1f
0g
1e
1`
0a
1_
1Z
0[
1Y
1T
0U
1S
1G
1N
1B
0O
1M
1A
0C
1I
1H
b101 !
b101 7
b11111111111111111 1
1<
b101 6
1=
1:
1@
1F
b1 5
b0 +
b101 -
b101 0
19
b1010 3
b0 %
b0 ,
b101 #
b101 *
b101 &
b0 (
#1050
b100 !
b100 7
b100 6
0=
0:
b1 +
b100 0
b1 %
b1 ,
b1 (
#1060
0I
0G
b11 !
b11 7
b11111111111111011 1
0B
1=
b11 6
1C
1:
0@
b0 +
b111 -
b111 0
b10 %
b10 ,
b10 (
#1070
b10 !
b10 7
b10 6
0=
0:
b1 +
b110 0
b11 %
b11 ,
b11 (
#1080
0/
1"
04
18"
0.
09"
17"
12"
03"
11"
1,"
0-"
1+"
1&"
0'"
1%"
1~
0!"
1}
1x
0y
1w
1r
0s
1q
1l
0m
1k
1f
0g
1e
1`
0a
1_
1Z
0[
1Y
1T
0U
1S
1N
1G
0O
1B
b1 !
b1 7
1M
1=
0C
b1 6
0I
b11111111111111111 1
1H
1:
1@
0F
b100 +
b101 -
b1 0
b100 %
b100 ,
b100 (
#1090
b0 !
b0 7
b0 6
0=
0:
b101 +
b0 0
b0 5
b101 %
b101 ,
b101 (
