ALU/oneBAdder/singleBAdder.v

module oneBAdder (
    input a, input b, input cIn, output s, output cOut
);
assign s = a ^ b ^ cIn;
assign cOut = (a & b) | (cIn & (a ^ b));
endmodule

ALU/alu.v
`include "oneBAdder/singleBAdder.v"
`define N 16 // I don't like parameters

/*
+--------+--------+
| OPCODE | Result |
+--------+--------+
| 0      | a + b  |
| 1      | a - b  |
| 2      | a & b  |
| 3      | a | b  |
| 4      | a ^ b  |
| 5      | a > b  |
| 6      | a << 1 |
| 7      | a >> 1 |
+--------+--------+
*/

module ALU(input [2 : 0] OPCODE, input [`N - 1 : 0]a, input [`N - 1 : 0] b, output reg [`N - 1 : 0] s, output cOut);

    wire[`N - 1 : 0] andOut, orOut, xorOut, shiftrOut, shiftlOut, gtOut, addOut;
    wire [`N : 0] tmp_carry; // 0 1 .. N, tmp_carry[N] is cout.

    assign tmp_carry[0] = OPCODE[0]; // OPCODE & 0x1
    assign cOut = tmp_carry[`N]; 

    genvar i;
    generate
        for(i = 0;i < `N;i = i + 1)begin : NbitAdder
            oneBAdder aa(
                .a(a[i]),
                .b(b[i] ^ OPCODE[0]), 
                .cIn(tmp_carry[i]),
                .cOut(tmp_carry[i + 1]),
                .s(addOut[i])
            );
        end
    endgenerate
    assign andOut = a & b;
    assign orOut = a | b;
    assign xorOut = a ^ b;
    assign shiftrOut = a >> 1;
    assign shiftlOut = a << 1;
    assign gtOut = a > b ? 1 : 0;
    always @(*) begin
        case (OPCODE)
            0, 1: s = addOut;
            2   : s = andOut;
            3   : s = orOut;
            4   : s = xorOut;
            5   : s = gtOut;
            6   : s = shiftlOut;
            7   : s = shiftrOut;
            default : s = 0;
        endcase
    end

endmodule

ALU/test.v
`include "alu.v"
`timescale 1ns/1ns



module test;
    reg [2 : 0] opcodeTest;
    reg [`N - 1 : 0]firstOperandTest, secondOperandTest;
    wire[`N - 1 : 0] resultTest;
    wire carryOut;
    ALU DUT(
        .OPCODE(opcodeTest),
        .a(firstOperandTest),
        .b(secondOperandTest),
        .cOut(carryOut),
        .s(resultTest)
    );

    wire result;
    integer opcode, firstOperand, secondOperand;
    initial begin
        $dumpfile("test.vcd");
        $dumpvars(0, test);
        for(opcode = 0;opcode < 8;opcode = opcode + 1)begin
            for(firstOperand = 0;firstOperand < 8;firstOperand = firstOperand + 1)begin
                for(secondOperand = 0;secondOperand < 8;secondOperand = secondOperand + 1)begin
                    opcodeTest = opcode; firstOperandTest = firstOperand; secondOperandTest = secondOperand;
                    opcodeTest = opcode;
                    #10;
                end
            end
        end
        $finish;
    end

endmodule

ALU/test.vcd
$date
	Sat Jun 15 22:02:39 2024
$end
$version
	Icarus Verilog
$end
$timescale
	1ns
$end
$scope module test $end
$var wire 16 ! resultTest [15:0] $end
$var wire 1 " carryOut $end
$var reg 16 # firstOperandTest [15:0] $end
$var reg 3 $ opcodeTest [2:0] $end
$var reg 16 % secondOperandTest [15:0] $end
$var integer 32 & firstOperand [31:0] $end
$var integer 32 ' opcode [31:0] $end
$var integer 32 ( secondOperand [31:0] $end
$scope module DUT $end
$var wire 3 ) OPCODE [2:0] $end
$var wire 16 * a [15:0] $end
$var wire 16 + andOut [15:0] $end
$var wire 16 , b [15:0] $end
$var wire 16 - orOut [15:0] $end
$var wire 16 . xorOut [15:0] $end
$var wire 17 / tmp_carry [16:0] $end
$var wire 16 0 shiftrOut [15:0] $end
$var wire 16 1 shiftlOut [15:0] $end
$var wire 16 2 gtOut [15:0] $end
$var wire 1 " cOut $end
$var wire 16 3 addOut [15:0] $end
$var reg 16 4 s [15:0] $end
$scope begin NbitAdder[0] $end
$var parameter 2 5 i $end
$scope module aa $end
$var wire 1 6 a $end
$var wire 1 7 b $end
$var wire 1 8 cIn $end
$var wire 1 9 cOut $end
$var wire 1 : s $end
$upscope $end
$upscope $end
$scope begin NbitAdder[1] $end
$var parameter 2 ; i $end
$scope module aa $end
$var wire 1 < a $end
$var wire 1 = b $end
$var wire 1 > cIn $end
$var wire 1 ? cOut $end
$var wire 1 @ s $end
$upscope $end
$upscope $end
$scope begin NbitAdder[2] $end
$var parameter 3 A i $end
$scope module aa $end
$var wire 1 B a $end
$var wire 1 C b $end
$var wire 1 D cIn $end
$var wire 1 E cOut $end
$var wire 1 F s $end
$upscope $end
$upscope $end
$scope begin NbitAdder[3] $end
$var parameter 3 G i $end
$scope module aa $end
$var wire 1 H a $end
$var wire 1 I b $end
$var wire 1 J cIn $end
$var wire 1 K cOut $end
$var wire 1 L s $end
$upscope $end
$upscope $end
$scope begin NbitAdder[4] $end
$var parameter 4 M i $end
$scope module aa $end
$var wire 1 N a $end
$var wire 1 O b $end
$var wire 1 P cIn $end
$var wire 1 Q cOut $end
$var wire 1 R s $end
$upscope $end
$upscope $end
$scope begin NbitAdder[5] $end
$var parameter 4 S i $end
$scope module aa $end
$var wire 1 T a $end
$var wire 1 U b $end
$var wire 1 V cIn $end
$var wire 1 W cOut $end
$var wire 1 X s $end
$upscope $end
$upscope $end
$scope begin NbitAdder[6] $end
$var parameter 4 Y i $end
$scope module aa $end
$var wire 1 Z a $end
$var wire 1 [ b $end
$var wire 1 \ cIn $end
$var wire 1 ] cOut $end
$var wire 1 ^ s $end
$upscope $end
$upscope $end
$scope begin NbitAdder[7] $end
$var parameter 4 _ i $end
$scope module aa $end
$var wire 1 ` a $end
$var wire 1 a b $end
$var wire 1 b cIn $end
$var wire 1 c cOut $end
$var wire 1 d s $end
$upscope $end
$upscope $end
$scope begin NbitAdder[8] $end
$var parameter 5 e i $end
$scope module aa $end
$var wire 1 f a $end
$var wire 1 g b $end
$var wire 1 h cIn $end
$var wire 1 i cOut $end
$var wire 1 j s $end
$upscope $end
$upscope $end
$scope begin NbitAdder[9] $end
$var parameter 5 k i $end
$scope module aa $end
$var wire 1 l a $end
$var wire 1 m b $end
$var wire 1 n cIn $end
$var wire 1 o cOut $end
$var wire 1 p s $end
$upscope $end
$upscope $end
$scope begin NbitAdder[10] $end
$var parameter 5 q i $end
$scope module aa $end
$var wire 1 r a $end
$var wire 1 s b $end
$var wire 1 t cIn $end
$var wire 1 u cOut $end
$var wire 1 v s $end
$upscope $end
$upscope $end
$scope begin NbitAdder[11] $end
$var parameter 5 w i $end
$scope module aa $end
$var wire 1 x a $end
$var wire 1 y b $end
$var wire 1 z cIn $end
$var wire 1 { cOut $end
$var wire 1 | s $end
$upscope $end
$upscope $end
$scope begin NbitAdder[12] $end
$var parameter 5 } i $end
$scope module aa $end
$var wire 1 ~ a $end
$var wire 1 !" b $end
$var wire 1 "" cIn $end
$var wire 1 #" cOut $end
$var wire 1 $" s $end
$upscope $end
$upscope $end
$scope begin NbitAdder[13] $end
$var parameter 5 %" i $end
$scope module aa $end
$var wire 1 &" a $end
$var wire 1 '" b $end
$var wire 1 (" cIn $end
$var wire 1 )" cOut $end
$var wire 1 *" s $end
$upscope $end
$upscope $end
$scope begin NbitAdder[14] $end
$var parameter 5 +" i $end
$scope module aa $end
$var wire 1 ," a $end
$var wire 1 -" b $end
$var wire 1 ." cIn $end
$var wire 1 /" cOut $end
$var wire 1 0" s $end
$upscope $end
$upscope $end
$scope begin NbitAdder[15] $end
$var parameter 5 1" i $end
$scope module aa $end
$var wire 1 2" a $end
$var wire 1 3" b $end
$var wire 1 4" cIn $end
$var wire 1 5" cOut $end
$var wire 1 6" s $end
$upscope $end
$upscope $end
$upscope $end
$upscope $end
$enddefinitions $end
$comment Show the parameter values. $end
$dumpall
b1111 1"
b1110 +"
b1101 %"
b1100 }
b1011 w
b1010 q
b1001 k
b1000 e
b111 _
b110 Y
b101 S
b100 M
b11 G
b10 A
b1 ;
b0 5
$end
#0
$dumpvars
06"
05"
04"
03"
02"
00"
0/"
0."
0-"
0,"
0*"
0)"
0("
0'"
0&"
0$"
0#"
0""
0!"
0~
0|
0{
0z
0y
0x
0v
0u
0t
0s
0r
0p
0o
0n
0m
0l
0j
0i
0h
0g
0f
0d
0c
0b
0a
0`
0^
0]
0\
0[
0Z
0X
0W
0V
0U
0T
0R
0Q
0P
0O
0N
0L
0K
0J
0I
0H
0F
0E
0D
0C
0B
0@
0?
0>
0=
0<
0:
09
08
07
06
b0 4
b0 3
b0 2
b0 1
b0 0
b0 /
b0 .
b0 -
b0 ,
b0 +
b0 *
b0 )
b0 (
b0 '
b0 &
b0 %
b0 $
b0 #
0"
b0 !
$end
#10
b1 !
b1 4
b1 3
1:
17
b1 -
b1 .
b1 %
b1 ,
b1 (
#20
b10 !
b10 4
0:
b10 3
1@
07
1=
b10 -
b10 .
b10 %
b10 ,
b10 (
#30
b11 !
b11 4
b11 3
1:
17
b11 -
b11 .
b11 %
b11 ,
b11 (
#40
b100 !
b100 4
0:
0@
b100 3
1F
07
0=
1C
b100 -
b100 .
b100 %
b100 ,
b100 (
#50
b101 !
b101 4
b101 3
1:
17
b101 -
b101 .
b101 %
b101 ,
b101 (
#60
b110 !
b110 4
0:
b110 3
1@
07
1=
b110 -
b110 .
b110 %
b110 ,
b110 (
#70
b111 !
b111 4
b111 3
1:
17
b111 -
b111 .
b111 %
b111 ,
b111 (
#80
0@
0F
b1 !
b1 4
0>
b1 3
1:
b0 /
09
07
0=
0C
b1 2
b1 -
b1 .
16
b10 1
b0 %
b0 ,
b1 #
b1 *
b1 &
b0 (
#90
1@
b10 !
b10 4
1>
b10 3
0:
b10 /
19
17
b1 +
b0 .
b0 2
b1 %
b1 ,
b1 (
#100
0F
0D
0>
b11 !
b11 4
0?
1:
b0 /
09
b11 3
1@
07
1=
b0 +
b11 -
b11 .
b10 %
b10 ,
b10 (
#110
1F
1D
1?
0@
b100 !
b100 4
1>
b100 3
0:
b110 /
19
17
b1 +
b10 .
b11 %
b11 ,
b11 (
#120
0L
0D
0J
0>
0?
b101 !
b101 4
0E
1:
b0 /
09
0@
b101 3
1F
07
0=
1C
b0 +
b101 -
b101 .
b100 %
b100 ,
b100 (
#130
1@
b110 !
b110 4
1>
b110 3
0:
b10 /
19
17
b1 +
b100 .
b101 %
b101 ,
b101 (
#140
0L
0J
0E
1F
0D
0>
b111 !
b111 4
0?
1:
b0 /
09
b111 3
1@
07
1=
b0 +
b111 -
b111 .
b110 %
b110 ,
b110 (
#150
1L
1J
1E
0F
1D
1?
0@
b1000 !
b1000 4
1>
b1000 3
0:
b1110 /
19
17
b1 +
b110 .
b111 %
b111 ,
b111 (
#160
0L
0J
0D
0E
0?
0F
0>
b10 !
b10 4
0:
b0 /
09
b10 3
1@
07
0=
0C
b1 2
b0 +
b10 -
b10 .
06
1<
b1 0
b100 1
b0 %
b0 ,
b10 #
b10 *
b10 &
b0 (
#170
b11 !
b11 4
b11 3
1:
17
b11 -
b11 .
b1 %
b1 ,
b1 (
#180
1F
b100 !
b100 4
1D
0:
b100 3
0@
b100 /
1?
07
1=
b10 +
b10 -
b0 .
b0 2
b10 %
b10 ,
b10 (
#190
b101 !
b101 4
b101 3
1:
17
b11 -
b1 .
b11 %
b11 ,
b11 (
#200
0L
0J
0D
b110 !
b110 4
0E
0:
1@
b0 /
0?
b110 3
1F
07
0=
1C
b0 +
b110 -
b110 .
b100 %
b100 ,
b100 (
#210
b111 !
b111 4
b111 3
1:
17
b111 -
b111 .
b101 %
b101 ,
b101 (
#220
1L
1J
1E
0F
b1000 !
b1000 4
1D
0:
b1000 3
0@
b1100 /
1?
07
1=
b10 +
b110 -
b100 .
b110 %
b110 ,
b110 (
#230
b1001 !
b1001 4
b1001 3
1:
17
b111 -
b101 .
b111 %
b111 ,
b111 (
#240
0D
0?
0L
1@
0J
0E
0F
b11 !
b11 4
0>
b11 3
1:
b0 /
09
07
0=
0C
b1 2
b0 +
b11 -
b11 .
16
b110 1
b0 %
b0 ,
b11 #
b11 *
b11 &
b0 (
#250
1F
1D
1?
0@
b100 !
b100 4
1>
b100 3
0:
b110 /
19
17
b1 +
b10 .
b1 %
b1 ,
b1 (
#260
0>
b101 !
b101 4
1:
b100 /
09
b101 3
0@
07
1=
b10 +
b1 .
b10 %
b10 ,
b10 (
#270
1@
b110 !
b110 4
1>
b110 3
0:
b110 /
19
17
b11 +
b0 .
b0 2
b11 %
b11 ,
b11 (
#280
0D
0?
0L
0J
0>
b111 !
b111 4
0E
1:
b0 /
09
1@
b111 3
1F
07
0=
1C
b0 +
b111 -
b111 .
b100 %
b100 ,
b100 (
#290
1L
1J
1E
0F
1D
1?
0@
b1000 !
b1000 4
1>
b1000 3
0:
b1110 /
19
17
b1 +
b110 .
b101 %
b101 ,
b101 (
#300
0>
b1001 !
b1001 4
1:
b1100 /
09
b1001 3
0@
07
1=
b10 +
b101 .
b110 %
b110 ,
b110 (
#310
1@
b1010 !
b1010 4
1>
b1010 3
0:
b1110 /
19
17
b11 +
b100 .
b111 %
b111 ,
b111 (
#320
0L
0J
0E
0D
0?
0>
b100 !
b100 4
0:
b0 /
09
0@
b100 3
1F
07
0=
0C
b1 2
b0 +
b100 -
06
0<
1B
b10 0
b1000 1
b0 %
b0 ,
b100 #
b100 *
b100 &
b0 (
#330
b101 !
b101 4
b101 3
1:
17
b101 -
b101 .
b1 %
b1 ,
b1 (
#340
b110 !
b110 4
0:
b110 3
1@
07
1=
b110 -
b110 .
b10 %
b10 ,
b10 (
#350
b111 !
b111 4
b111 3
1:
17
b111 -
b111 .
b11 %
b11 ,
b11 (
#360
1L
b1000 !
b1000 4
1J
0:
0@
b1000 3
0F
b1000 /
1E
07
0=
1C
b100 +
b100 -
b0 .
b0 2
b100 %
b100 ,
b100 (
#370
b1001 !
b1001 4
b1001 3
1:
17
b101 -
b1 .
b101 %
b101 ,
b101 (
#380
b1010 !
b1010 4
0:
b1010 3
1@
07
1=
b110 -
b10 .
b110 %
b110 ,
b110 (
#390
b1011 !
b1011 4
b1011 3
1:
17
b111 -
b11 .
b111 %
b111 ,
b111 (
#400
0@
0L
0J
1F
0E
b101 !
b101 4
0>
b101 3
1:
b0 /
09
07
0=
0C
b1 2
b0 +
b101 -
b101 .
16
b1010 1
b0 %
b0 ,
b101 #
b101 *
b101 &
b0 (
#410
1@
b110 !
b110 4
1>
b110 3
0:
b10 /
19
17
b1 +
b100 .
b1 %
b1 ,
b1 (
#420
0L
0J
0E
1F
0D
0>
b111 !
b111 4
0?
1:
b0 /
09
b111 3
1@
07
1=
b0 +
b111 -
b111 .
b10 %
b10 ,
b10 (
#430
1L
1J
1E
0F
1D
1?
0@
b1000 !
b1000 4
1>
b1000 3
0:
b1110 /
19
17
b1 +
b110 .
b11 %
b11 ,
b11 (
#440
0D
0>
0?
b1001 !
b1001 4
1:
b1000 /
09
0@
b1001 3
0F
07
0=
1C
b100 +
b101 -
b1 .
b100 %
b100 ,
b100 (
#450
1@
b1010 !
b1010 4
1>
b1010 3
0:
b1010 /
19
17
b101 +
b0 .
b0 2
b101 %
b101 ,
b101 (
#460
0F
0D
0>
b1011 !
b1011 4
0?
1:
b1000 /
09
b1011 3
1@
07
1=
b100 +
b111 -
b11 .
b110 %
b110 ,
b110 (
#470
1F
1D
1?
0@
b1100 !
b1100 4
1>
b1100 3
0:
b1110 /
19
17
b101 +
b10 .
b111 %
b111 ,
b111 (
#480
0L
0J
0E
0D
0?
1F
0>
b110 !
b110 4
0:
b0 /
09
b110 3
1@
07
0=
0C
b1 2
b0 +
b110 -
b110 .
06
1<
b11 0
b1100 1
b0 %
b0 ,
b110 #
b110 *
b110 &
b0 (
#490
b111 !
b111 4
b111 3
1:
17
b111 -
b111 .
b1 %
b1 ,
b1 (
#500
1L
1J
1E
0F
b1000 !
b1000 4
1D
0:
b1000 3
0@
b1100 /
1?
07
1=
b10 +
b110 -
b100 .
b10 %
b10 ,
b10 (
#510
b1001 !
b1001 4
b1001 3
1:
17
b111 -
b101 .
b11 %
b11 ,
b11 (
#520
0D
b1010 !
b1010 4
0:
1@
b1000 /
0?
b1010 3
0F
07
0=
1C
b100 +
b110 -
b10 .
b100 %
b100 ,
b100 (
#530
b1011 !
b1011 4
b1011 3
1:
17
b111 -
b11 .
b101 %
b101 ,
b101 (
#540
1F
b1100 !
b1100 4
1D
0:
b1100 3
0@
b1100 /
1?
07
1=
b110 +
b110 -
b0 .
b0 2
b110 %
b110 ,
b110 (
#550
b1101 !
b1101 4
b1101 3
1:
17
b111 -
b1 .
b111 %
b111 ,
b111 (
#560
0L
0J
0E
0D
0?
1@
1F
b111 !
b111 4
0>
b111 3
1:
b0 /
09
07
0=
0C
b1 2
b0 +
b111 .
16
b1110 1
b0 %
b0 ,
b111 #
b111 *
b111 &
b0 (
#570
1L
1J
1E
0F
1D
1?
0@
b1000 !
b1000 4
1>
b1000 3
0:
b1110 /
19
17
b1 +
b110 .
b1 %
b1 ,
b1 (
#580
0>
b1001 !
b1001 4
1:
b1100 /
09
b1001 3
0@
07
1=
b10 +
b101 .
b10 %
b10 ,
b10 (
#590
1@
b1010 !
b1010 4
1>
b1010 3
0:
b1110 /
19
17
b11 +
b100 .
b11 %
b11 ,
b11 (
#600
0D
0?
0>
b1011 !
b1011 4
1:
b1000 /
09
1@
b1011 3
0F
07
0=
1C
b100 +
b11 .
b100 %
b100 ,
b100 (
#610
1F
1D
1?
0@
b1100 !
b1100 4
1>
b1100 3
0:
b1110 /
19
17
b101 +
b10 .
b101 %
b101 ,
b101 (
#620
0>
b1101 !
b1101 4
1:
b1100 /
09
b1101 3
0@
07
1=
b110 +
b1 .
b110 %
b110 ,
b110 (
#630
1@
b1110 !
b1110 4
1>
b1110 3
0:
b1110 /
19
17
b111 +
b0 .
b0 2
b111 %
b111 ,
b111 (
#640
1"
15"
14"
1/"
1."
1)"
1("
1#"
1""
1{
1z
1u
1t
1o
1n
1i
1h
1c
1b
1]
1\
1W
1V
1Q
1P
1K
b0 !
b0 4
0L
0R
0X
0^
0d
0j
0p
0v
0|
0$"
0*"
00"
06"
0@
b0 3
0F
1I
1O
1U
1[
1a
1g
1m
1s
1y
1!"
1'"
1-"
13"
18
b0 +
b0 -
06
0<
0B
b0 0
b0 1
b11111111111111111 /
b0 %
b0 ,
b0 #
b0 *
b1 $
b1 )
b1 '
b0 &
b0 (
#650
0"
05"
16"
04"
0/"
10"
0."
0)"
1*"
0("
0#"
1$"
0""
0{
1|
0z
0u
1v
0t
0o
1p
0n
0i
1j
0h
0c
1d
0b
0]
1^
0\
0W
1X
0V
0Q
1R
0P
0K
1L
0J
0E
1F
0D
0?
1@
0>
b1111111111111111 !
b1111111111111111 4
b1 /
09
b1111111111111111 3
1:
07
b1 -
b1 .
b1 %
b1 ,
b1 (
#660
1>
b11 /
19
b1111111111111110 !
b1111111111111110 4
0:
b1111111111111110 3
1@
17
0=
b10 -
b10 .
b10 %
b10 ,
b10 (
#670
0@
0>
b1111111111111101 !
b1111111111111101 4
b1 /
09
b1111111111111101 3
1:
07
b11 -
b11 .
b11 %
b11 ,
b11 (
#680
1D
1?
1>
b111 /
19
b1111111111111100 !
b1111111111111100 4
0:
0@
b1111111111111100 3
1F
17
1=
0C
b100 -
b100 .
b100 %
b100 ,
b100 (
#690
0F
0D
0?
1@
0>
b1111111111111011 !
b1111111111111011 4
b1 /
09
b1111111111111011 3
1:
07
b101 -
b101 .
b101 %
b101 ,
b101 (
#700
1>
b11 /
19
b1111111111111010 !
b1111111111111010 4
0:
b1111111111111010 3
1@
17
0=
b110 -
b110 .
b110 %
b110 ,
b110 (
#710
0@
0>
b1111111111111001 !
b1111111111111001 4
b1 /
09
b1111111111111001 3
1:
07
b111 -
b111 .
b111 %
b111 ,
b111 (
#720
1"
15"
06"
14"
1/"
00"
1."
1)"
0*"
1("
1#"
0$"
1""
1{
0|
1z
1u
0v
1t
1o
0p
1n
1i
0j
1h
1c
0d
1b
1]
0^
1\
1W
0X
1V
1Q
0R
1P
1K
0L
1J
1E
1D
1?
1>
0@
0F
b1 !
b1 4
b11111111111111111 /
19
b1 3
1:
17
1=
1C
b1 2
b1 -
b1 .
16
b10 1
b0 %
b0 ,
b1 #
b1 *
b1 &
b0 (
#730
b0 !
b0 4
b0 3
0:
07
b1 +
b0 .
b0 2
b1 %
b1 ,
b1 (
#740
0"
05"
16"
04"
0/"
10"
0."
0)"
1*"
0("
0#"
1$"
0""
0{
1|
0z
0u
1v
0t
0o
1p
0n
0i
1j
0h
0c
1d
0b
0]
1^
0\
0W
1X
0V
0Q
1R
0P
0K
1L
0J
0E
1F
0D
b1111111111111111 !
b1111111111111111 4
b11 /
0?
1:
b1111111111111111 3
1@
17
0=
b0 +
b11 -
b11 .
b10 %
b10 ,
b10 (
#750
b1111111111111110 !
b1111111111111110 4
b1111111111111110 3
0:
07
b1 +
b10 .
b11 %
b11 ,
b11 (
#760
1D
b111 /
1?
b1111111111111101 !
b1111111111111101 4
1:
0@
b1111111111111101 3
1F
17
1=
0C
b0 +
b101 -
b101 .
b100 %
b100 ,
b100 (
#770
b1111111111111100 !
b1111111111111100 4
b1111111111111100 3
0:
07
b1 +
b100 .
b101 %
b101 ,
b101 (
#780
0F
0D
b1111111111111011 !
b1111111111111011 4
b11 /
0?
1:
b1111111111111011 3
1@
17
0=
b0 +
b111 -
b111 .
b110 %
b110 ,
b110 (
#790
b1111111111111010 !
b1111111111111010 4
b1111111111111010 3
0:
07
b1 +
b110 .
b111 %
b111 ,
b111 (
#800
1"
15"
06"
14"
1/"
00"
1."
1)"
0*"
1("
1#"
0$"
1""
1{
0|
1z
1u
0v
1t
1o
0p
1n
1i
0j
1h
1c
0d
1b
1]
0^
1\
1W
0X
1V
1Q
0R
1P
1K
0L
1J
1E
1>
1D
0F
19
b10 !
b10 4
b11111111111111111 /
1?
0:
b10 3
1@
17
1=
1C
b1 2
b0 +
b10 -
b10 .
06
1<
b1 0
b100 1
b0 %
b0 ,
b10 #
b10 *
b10 &
b0 (
#810
0@
0>
b1 !
b1 4
b11111111111111101 /
09
b1 3
1:
07
b11 -
b11 .
b1 %
b1 ,
b1 (
#820
1"
15"
06"
14"
1/"
00"
1."
1)"
0*"
1("
1#"
0$"
1""
1{
0|
1z
1u
0v
1t
1o
0p
1n
1i
0j
1h
1c
0d
1b
1]
0^
1\
1W
0X
1V
1Q
0R
1P
1K
0L
1J
1E
1>
0F
19
b0 !
b0 4
1D
0:
b0 3
0@
b11111111111111111 /
1?
17
0=
b10 +
b10 -
b0 .
b0 2
b10 %
b10 ,
b10 (
#830
0"
05"
16"
04"
0/"
10"
0."
0)"
1*"
0("
0#"
1$"
0""
0{
1|
0z
0u
1v
0t
0o
1p
0n
0i
1j
0h
0c
1d
0b
0]
1^
0\
0W
1X
0V
0Q
1R
0P
0K
1L
0J
0E
1F
0D
0?
1@
0>
b1111111111111111 !
b1111111111111111 4
b1 /
09
b1111111111111111 3
1:
07
b11 -
b1 .
b11 %
b11 ,
b11 (
#840
1>
19
1D
b1111111111111110 !
b1111111111111110 4
0:
1@
b111 /
1?
b1111111111111110 3
1F
17
1=
0C
b0 +
b110 -
b110 .
b100 %
b100 ,
b100 (
#850
0@
0>
b1111111111111101 !
b1111111111111101 4
b101 /
09
b1111111111111101 3
1:
07
b111 -
b111 .
b101 %
b101 ,
b101 (
#860
1>
1F
19
b1111111111111100 !
b1111111111111100 4
1D
0:
b1111111111111100 3
0@
b111 /
1?
17
0=
b10 +
b110 -
b100 .
b110 %
b110 ,
b110 (
#870
0F
0D
0?
1@
0>
b1111111111111011 !
b1111111111111011 4
b1 /
09
b1111111111111011 3
1:
07
b111 -
b101 .
b111 %
b111 ,
b111 (
#880
1"
15"
06"
14"
1/"
00"
1."
1)"
0*"
1("
1#"
0$"
1""
1{
0|
1z
1u
0v
1t
1o
0p
1n
1i
0j
1h
1c
0d
1b
1]
0^
1\
1W
0X
1V
1Q
0R
1P
1K
0L
1J
1E
1D
1>
1@
1?
0F
b11 !
b11 4
b11111111111111111 /
19
b11 3
1:
17
1=
1C
b1 2
b0 +
b11 -
b11 .
16
b110 1
b0 %
b0 ,
b11 #
b11 *
b11 &
b0 (
#890
b10 !
b10 4
b10 3
0:
07
b1 +
b10 .
b1 %
b1 ,
b1 (
#900
b1 !
b1 4
1:
b1 3
0@
17
0=
b10 +
b1 .
b10 %
b10 ,
b10 (
#910
b0 !
b0 4
b0 3
0:
07
b11 +
b0 .
b0 2
b11 %
b11 ,
b11 (
#920
0"
05"
16"
04"
0/"
10"
0."
0)"
1*"
0("
0#"
1$"
0""
0{
1|
0z
0u
1v
0t
0o
1p
0n
0i
1j
0h
0c
1d
0b
0]
1^
0\
0W
1X
0V
0Q
1R
0P
0K
1L
0J
b1111111111111111 !
b1111111111111111 4
b111 /
0E
1:
1@
b1111111111111111 3
1F
17
1=
0C
b0 +
b111 -
b111 .
b100 %
b100 ,
b100 (
#930
b1111111111111110 !
b1111111111111110 4
b1111111111111110 3
0:
07
b1 +
b110 .
b101 %
b101 ,
b101 (
#940
b1111111111111101 !
b1111111111111101 4
1:
b1111111111111101 3
0@
17
0=
b10 +
b101 .
b110 %
b110 ,
b110 (
#950
b1111111111111100 !
b1111111111111100 4
b1111111111111100 3
0:
07
b11 +
b100 .
b111 %
b111 ,
b111 (
#960
1"
15"
06"
14"
1/"
00"
1."
1)"
0*"
1("
1#"
0$"
1""
1{
0|
1z
1u
0v
1t
1o
0p
1n
1i
0j
1h
1c
0d
1b
1]
0^
1\
1W
0X
1V
1Q
0R
1P
1K
0L
1>
1D
1J
19
1?
b100 !
b100 4
b11111111111111111 /
1E
0:
0@
b100 3
1F
17
1=
1C
b1 2
b0 +
b100 -
06
0<
1B
b10 0
b1000 1
b0 %
b0 ,
b100 #
b100 *
b100 &
b0 (
#970
0F
0D
0?
1@
0>
b11 !
b11 4
b11111111111111001 /
09
b11 3
1:
07
b101 -
b101 .
b1 %
b1 ,
b1 (
#980
1>
b11111111111111011 /
19
b10 !
b10 4
0:
b10 3
1@
17
0=
b110 -
b110 .
b10 %
b10 ,
b10 (
#990
0@
0>
b1 !
b1 4
b11111111111111001 /
09
b1 3
1:
07
b111 -
b111 .
b11 %
b11 ,
b11 (
#1000
1"
15"
06"
14"
1/"
00"
1."
1)"
0*"
1("
1#"
0$"
1""
1{
0|
1z
1u
0v
1t
1o
0p
1n
1i
0j
1h
1c
0d
1b
1]
0^
1\
1W
0X
1V
1Q
1D
0R
1?
1P
1K
1>
0L
19
b0 !
b0 4
1J
0:
0@
b0 3
0F
b11111111111111111 /
1E
17
1=
0C
b100 +
b100 -
b0 .
b0 2
b100 %
b100 ,
b100 (
#1010
0"
05"
16"
04"
0/"
10"
0."
0)"
1*"
0("
0#"
1$"
0""
0{
1|
0z
0u
1v
0t
0o
1p
0n
0i
1j
0h
0c
1d
0b
0]
1^
0\
0W
1X
0V
0Q
1R
0P
0K
1L
0J
0E
1F
0D
0?
1@
0>
b1111111111111111 !
b1111111111111111 4
b1 /
09
b1111111111111111 3
1:
07
b101 -
b1 .
b101 %
b101 ,
b101 (
#1020
1>
b11 /
19
b1111111111111110 !
b1111111111111110 4
0:
b1111111111111110 3
1@
17
0=
b110 -
b10 .
b110 %
b110 ,
b110 (
#1030
0@
0>
b1111111111111101 !
b1111111111111101 4
b1 /
09
b1111111111111101 3
1:
07
b111 -
b11 .
b111 %
b111 ,
b111 (
#1040
1"
15"
06"
14"
1/"
00"
1."
1)"
0*"
1("
1#"
0$"
1""
1{
0|
1z
1u
0v
1t
1o
0p
1n
1i
0j
1h
1c
0d
1b
1]
0^
1\
1W
0X
1V
1Q
0R
1P
1D
1K
1?
0L
1J
1>
0@
1F
1E
b101 !
b101 4
b11111111111111111 /
19
b101 3
1:
17
1=
1C
b1 2
b0 +
b101 -
b101 .
16
b1010 1
b0 %
b0 ,
b101 #
b101 *
b101 &
b0 (
#1050
b100 !
b100 4
b100 3
0:
07
b1 +
b100 .
b1 %
b1 ,
b1 (
#1060
0F
0D
b11 !
b11 4
b11111111111111011 /
0?
1:
b11 3
1@
17
0=
b0 +
b111 -
b111 .
b10 %
b10 ,
b10 (
#1070
b10 !
b10 4
b10 3
0:
07
b1 +
b110 .
b11 %
b11 ,
b11 (
#1080
1"
15"
06"
14"
1/"
00"
1."
1)"
0*"
1("
1#"
0$"
1""
1{
0|
1z
1u
0v
1t
1o
0p
1n
1i
0j
1h
1c
0d
1b
1]
0^
1\
1W
0X
1V
1Q
0R
1P
1K
1D
0L
1?
b1 !
b1 4
1J
1:
0@
b1 3
0F
b11111111111111111 /
1E
17
1=
0C
b100 +
b101 -
b1 .
b100 %
b100 ,
b100 (
#1090
b0 !
b0 4
b0 3
0:
07
b101 +
b0 .
b0 2
b101 %
b101 ,
b101 (
#1100
0"
05"
16"
04"
0/"
10"
0."
0)"
1*"
0("
0#"
1$"
0""
0{
1|
0z
0u
1v
0t
0o
1p
0n
0i
1j
0h
0c
1d
0b
0]
1^
0\
0W
1X
0V
0Q
1R
0P
0K
1L
0J
0E
1F
0D
b1111111111111111 !
b1111111111111111 4
b11 /
0?
1:
b1111111111111111 3
1@
17
0=
b100 +
b111 -
b11 .
b110 %
b110 ,
b110 (
#1110
b1111111111111110 !
b1111111111111110 4
b1111111111111110 3
0:
07
b101 +
b10 .
b111 %
b111 ,
b111 (
#1120
1"
15"
06"
14"
1/"
00"
1."
1)"
0*"
1("
1#"
0$"
1""
1{
0|
1z
1u
0v
1t
1o
0p
1n
1i
0j
1h
1c
0d
1b
1]
0^
1\
1W
0X
1V
1Q
0R
1P
1K
0L
1J
1>
1D
1F
1E
19
b110 !
b110 4
b11111111111111111 /
1?
0:
b110 3
1@
17
1=
1C
b1 2
b0 +
b110 -
b110 .
06
1<
b11 0
b1100 1
b0 %
b0 ,
b110 #
b110 *
b110 &
b0 (
#1130
0@
0>
b101 !
b101 4
b11111111111111101 /
09
b101 3
1:
07
b111 -
b111 .
b1 %
b1 ,
b1 (
